
{"success":true,"status":200,"msg":"","instance":{"id":52,"title":"<i>Celosia trigyna <\u002fi>L. ","taxonConcept":{"id":129,"name":"Celosia trigyna L.","canonicalForm":"Celosia trigyna","italicisedForm":"<i>Celosia trigyna <\u002fi>L. ","rank":"Species","nameStatus":"accepted","sourceDatabase":"Thomas Le_bourgeois","defaultHierarchy":[{"id":1,"lid":129,"rank":0,"name":"Plantae","canonical_form":"Plantae"},{"id":2,"lid":129,"rank":1,"name":"Tracheophyta","canonical_form":"Tracheophyta"},{"id":3,"lid":129,"rank":2,"name":"Magnoliopsida","canonical_form":"Magnoliopsida"},{"id":28,"lid":129,"rank":3,"name":"Caryophyllales","canonical_form":"Caryophyllales"},{"id":29,"lid":129,"rank":5,"name":"Amaranthaceae","canonical_form":"Amaranthaceae"},{"id":127,"lid":129,"rank":7,"name":"Celosia","canonical_form":"Celosia"},{"id":129,"lid":129,"rank":9,"name":"Celosia trigyna L.","canonical_form":"Celosia trigyna"}],"group":{"id":10,"name":"Plants","groupOrder":0},"parentName":null,"position":"Clean","speciesId":52},"taxonRegistry":[{"clasification":{"id":2,"name":"Author Contributed Taxonomy Hierarchy","citation":"Hierarchy contributed by the species page author"},"hierarchies":[{"id":1,"name":"Plantae","canonicalForm":"Plantae","italicisedForm":"<i>Plantae<\u002fi>","rank":"Kingdom","nameStatus":"accepted","sourceDatabase":"","defaultHierarchy":[{"id":1,"lid":1,"rank":0,"name":"Plantae","canonical_form":"Plantae"}],"group":{"id":10,"name":"Plants","groupOrder":0},"parentName":null,"position":"Clean","speciesId":372},{"id":2,"name":"Tracheophyta","canonicalForm":"Tracheophyta","italicisedForm":"<i>Tracheophyta<\u002fi>","rank":"Phylum","nameStatus":"accepted","sourceDatabase":"","defaultHierarchy":[{"id":1,"lid":2,"rank":0,"name":"Plantae","canonical_form":"Plantae"},{"id":2,"lid":2,"rank":1,"name":"Tracheophyta","canonical_form":"Tracheophyta"}],"group":{"id":10,"name":"Plants","groupOrder":0},"parentName":null,"position":"Clean","speciesId":371},{"id":3,"name":"Magnoliopsida","canonicalForm":"Magnoliopsida","italicisedForm":"<i>Magnoliopsida<\u002fi>","rank":"Class","nameStatus":"accepted","sourceDatabase":"","defaultHierarchy":[{"id":1,"lid":3,"rank":0,"name":"Plantae","canonical_form":"Plantae"},{"id":2,"lid":3,"rank":1,"name":"Tracheophyta","canonical_form":"Tracheophyta"},{"id":3,"lid":3,"rank":2,"name":"Magnoliopsida","canonical_form":"Magnoliopsida"}],"group":{"id":10,"name":"Plants","groupOrder":0},"parentName":null,"position":"Clean","speciesId":374},{"id":29,"name":"Amaranthaceae","canonicalForm":"Amaranthaceae","italicisedForm":"<i>Amaranthaceae<\u002fi>","rank":"Family","nameStatus":"accepted","sourceDatabase":"","defaultHierarchy":[{"id":1,"lid":29,"rank":0,"name":"Plantae","canonical_form":"Plantae"},{"id":2,"lid":29,"rank":1,"name":"Tracheophyta","canonical_form":"Tracheophyta"},{"id":3,"lid":29,"rank":2,"name":"Magnoliopsida","canonical_form":"Magnoliopsida"},{"id":28,"lid":29,"rank":3,"name":"Caryophyllales","canonical_form":"Caryophyllales"},{"id":29,"lid":29,"rank":5,"name":"Amaranthaceae","canonical_form":"Amaranthaceae"}],"group":{"id":10,"name":"Plants","groupOrder":0},"parentName":null,"position":"Clean","speciesId":null},{"id":127,"name":"Celosia","canonicalForm":"Celosia","italicisedForm":"<i>Celosia<\u002fi>","rank":"Genus","nameStatus":"accepted","sourceDatabase":"","defaultHierarchy":[{"id":1,"lid":127,"rank":0,"name":"Plantae","canonical_form":"Plantae"},{"id":2,"lid":127,"rank":1,"name":"Tracheophyta","canonical_form":"Tracheophyta"},{"id":3,"lid":127,"rank":2,"name":"Magnoliopsida","canonical_form":"Magnoliopsida"},{"id":28,"lid":127,"rank":3,"name":"Caryophyllales","canonical_form":"Caryophyllales"},{"id":29,"lid":127,"rank":5,"name":"Amaranthaceae","canonical_form":"Amaranthaceae"},{"id":127,"lid":127,"rank":7,"name":"Celosia","canonical_form":"Celosia"}],"group":{"id":10,"name":"Plants","groupOrder":0},"parentName":null,"position":"Clean","speciesId":null},{"id":129,"name":"Celosia trigyna L.","canonicalForm":"Celosia trigyna","italicisedForm":"<i>Celosia trigyna <\u002fi>L. ","rank":"Species","nameStatus":"accepted","sourceDatabase":"Thomas Le_bourgeois","defaultHierarchy":[{"id":1,"lid":129,"rank":0,"name":"Plantae","canonical_form":"Plantae"},{"id":2,"lid":129,"rank":1,"name":"Tracheophyta","canonical_form":"Tracheophyta"},{"id":3,"lid":129,"rank":2,"name":"Magnoliopsida","canonical_form":"Magnoliopsida"},{"id":28,"lid":129,"rank":3,"name":"Caryophyllales","canonical_form":"Caryophyllales"},{"id":29,"lid":129,"rank":5,"name":"Amaranthaceae","canonical_form":"Amaranthaceae"},{"id":127,"lid":129,"rank":7,"name":"Celosia","canonical_form":"Celosia"},{"id":129,"lid":129,"rank":9,"name":"Celosia trigyna L.","canonical_form":"Celosia trigyna"}],"group":{"id":10,"name":"Plants","groupOrder":0},"parentName":null,"position":"Clean","speciesId":52}]},{"clasification":{"id":6,"name":"WIKWIO Taxonomy Hierarchy","citation":null},"hierarchies":[{"id":1,"name":"Plantae","canonicalForm":"Plantae","italicisedForm":"<i>Plantae<\u002fi>","rank":"Kingdom","nameStatus":"accepted","sourceDatabase":"","defaultHierarchy":[{"id":1,"lid":1,"rank":0,"name":"Plantae","canonical_form":"Plantae"}],"group":{"id":10,"name":"Plants","groupOrder":0},"parentName":null,"position":"Clean","speciesId":372},{"id":2,"name":"Tracheophyta","canonicalForm":"Tracheophyta","italicisedForm":"<i>Tracheophyta<\u002fi>","rank":"Phylum","nameStatus":"accepted","sourceDatabase":"","defaultHierarchy":[{"id":1,"lid":2,"rank":0,"name":"Plantae","canonical_form":"Plantae"},{"id":2,"lid":2,"rank":1,"name":"Tracheophyta","canonical_form":"Tracheophyta"}],"group":{"id":10,"name":"Plants","groupOrder":0},"parentName":null,"position":"Clean","speciesId":371},{"id":3,"name":"Magnoliopsida","canonicalForm":"Magnoliopsida","italicisedForm":"<i>Magnoliopsida<\u002fi>","rank":"Class","nameStatus":"accepted","sourceDatabase":"","defaultHierarchy":[{"id":1,"lid":3,"rank":0,"name":"Plantae","canonical_form":"Plantae"},{"id":2,"lid":3,"rank":1,"name":"Tracheophyta","canonical_form":"Tracheophyta"},{"id":3,"lid":3,"rank":2,"name":"Magnoliopsida","canonical_form":"Magnoliopsida"}],"group":{"id":10,"name":"Plants","groupOrder":0},"parentName":null,"position":"Clean","speciesId":374},{"id":28,"name":"Caryophyllales","canonicalForm":"Caryophyllales","italicisedForm":"<i>Caryophyllales<\u002fi>","rank":"Order","nameStatus":"accepted","sourceDatabase":"","defaultHierarchy":[{"id":1,"lid":28,"rank":0,"name":"Plantae","canonical_form":"Plantae"},{"id":2,"lid":28,"rank":1,"name":"Tracheophyta","canonical_form":"Tracheophyta"},{"id":3,"lid":28,"rank":2,"name":"Magnoliopsida","canonical_form":"Magnoliopsida"},{"id":28,"lid":28,"rank":3,"name":"Caryophyllales","canonical_form":"Caryophyllales"}],"group":{"id":10,"name":"Plants","groupOrder":0},"parentName":null,"position":"Clean","speciesId":null},{"id":29,"name":"Amaranthaceae","canonicalForm":"Amaranthaceae","italicisedForm":"<i>Amaranthaceae<\u002fi>","rank":"Family","nameStatus":"accepted","sourceDatabase":"","defaultHierarchy":[{"id":1,"lid":29,"rank":0,"name":"Plantae","canonical_form":"Plantae"},{"id":2,"lid":29,"rank":1,"name":"Tracheophyta","canonical_form":"Tracheophyta"},{"id":3,"lid":29,"rank":2,"name":"Magnoliopsida","canonical_form":"Magnoliopsida"},{"id":28,"lid":29,"rank":3,"name":"Caryophyllales","canonical_form":"Caryophyllales"},{"id":29,"lid":29,"rank":5,"name":"Amaranthaceae","canonical_form":"Amaranthaceae"}],"group":{"id":10,"name":"Plants","groupOrder":0},"parentName":null,"position":"Clean","speciesId":null},{"id":127,"name":"Celosia","canonicalForm":"Celosia","italicisedForm":"<i>Celosia<\u002fi>","rank":"Genus","nameStatus":"accepted","sourceDatabase":"","defaultHierarchy":[{"id":1,"lid":127,"rank":0,"name":"Plantae","canonical_form":"Plantae"},{"id":2,"lid":127,"rank":1,"name":"Tracheophyta","canonical_form":"Tracheophyta"},{"id":3,"lid":127,"rank":2,"name":"Magnoliopsida","canonical_form":"Magnoliopsida"},{"id":28,"lid":127,"rank":3,"name":"Caryophyllales","canonical_form":"Caryophyllales"},{"id":29,"lid":127,"rank":5,"name":"Amaranthaceae","canonical_form":"Amaranthaceae"},{"id":127,"lid":127,"rank":7,"name":"Celosia","canonical_form":"Celosia"}],"group":{"id":10,"name":"Plants","groupOrder":0},"parentName":null,"position":"Clean","speciesId":null},{"id":129,"name":"Celosia trigyna L.","canonicalForm":"Celosia trigyna","italicisedForm":"<i>Celosia trigyna <\u002fi>L. ","rank":"Species","nameStatus":"accepted","sourceDatabase":"Thomas Le_bourgeois","defaultHierarchy":[{"id":1,"lid":129,"rank":0,"name":"Plantae","canonical_form":"Plantae"},{"id":2,"lid":129,"rank":1,"name":"Tracheophyta","canonical_form":"Tracheophyta"},{"id":3,"lid":129,"rank":2,"name":"Magnoliopsida","canonical_form":"Magnoliopsida"},{"id":28,"lid":129,"rank":3,"name":"Caryophyllales","canonical_form":"Caryophyllales"},{"id":29,"lid":129,"rank":5,"name":"Amaranthaceae","canonical_form":"Amaranthaceae"},{"id":127,"lid":129,"rank":7,"name":"Celosia","canonical_form":"Celosia"},{"id":129,"lid":129,"rank":9,"name":"Celosia trigyna L.","canonical_form":"Celosia trigyna"}],"group":{"id":10,"name":"Plants","groupOrder":0},"parentName":null,"position":"Clean","speciesId":52}]},{"clasification":{"id":7,"name":"Catalogue of Life Taxonomy Hierarchy","citation":null},"hierarchies":[{"id":1,"name":"Plantae","canonicalForm":"Plantae","italicisedForm":"<i>Plantae<\u002fi>","rank":"Kingdom","nameStatus":"accepted","sourceDatabase":"","defaultHierarchy":[{"id":1,"lid":1,"rank":0,"name":"Plantae","canonical_form":"Plantae"}],"group":{"id":10,"name":"Plants","groupOrder":0},"parentName":null,"position":"Clean","speciesId":372},{"id":2,"name":"Tracheophyta","canonicalForm":"Tracheophyta","italicisedForm":"<i>Tracheophyta<\u002fi>","rank":"Phylum","nameStatus":"accepted","sourceDatabase":"","defaultHierarchy":[{"id":1,"lid":2,"rank":0,"name":"Plantae","canonical_form":"Plantae"},{"id":2,"lid":2,"rank":1,"name":"Tracheophyta","canonical_form":"Tracheophyta"}],"group":{"id":10,"name":"Plants","groupOrder":0},"parentName":null,"position":"Clean","speciesId":371},{"id":3,"name":"Magnoliopsida","canonicalForm":"Magnoliopsida","italicisedForm":"<i>Magnoliopsida<\u002fi>","rank":"Class","nameStatus":"accepted","sourceDatabase":"","defaultHierarchy":[{"id":1,"lid":3,"rank":0,"name":"Plantae","canonical_form":"Plantae"},{"id":2,"lid":3,"rank":1,"name":"Tracheophyta","canonical_form":"Tracheophyta"},{"id":3,"lid":3,"rank":2,"name":"Magnoliopsida","canonical_form":"Magnoliopsida"}],"group":{"id":10,"name":"Plants","groupOrder":0},"parentName":null,"position":"Clean","speciesId":374},{"id":28,"name":"Caryophyllales","canonicalForm":"Caryophyllales","italicisedForm":"<i>Caryophyllales<\u002fi>","rank":"Order","nameStatus":"accepted","sourceDatabase":"","defaultHierarchy":[{"id":1,"lid":28,"rank":0,"name":"Plantae","canonical_form":"Plantae"},{"id":2,"lid":28,"rank":1,"name":"Tracheophyta","canonical_form":"Tracheophyta"},{"id":3,"lid":28,"rank":2,"name":"Magnoliopsida","canonical_form":"Magnoliopsida"},{"id":28,"lid":28,"rank":3,"name":"Caryophyllales","canonical_form":"Caryophyllales"}],"group":{"id":10,"name":"Plants","groupOrder":0},"parentName":null,"position":"Clean","speciesId":null},{"id":29,"name":"Amaranthaceae","canonicalForm":"Amaranthaceae","italicisedForm":"<i>Amaranthaceae<\u002fi>","rank":"Family","nameStatus":"accepted","sourceDatabase":"","defaultHierarchy":[{"id":1,"lid":29,"rank":0,"name":"Plantae","canonical_form":"Plantae"},{"id":2,"lid":29,"rank":1,"name":"Tracheophyta","canonical_form":"Tracheophyta"},{"id":3,"lid":29,"rank":2,"name":"Magnoliopsida","canonical_form":"Magnoliopsida"},{"id":28,"lid":29,"rank":3,"name":"Caryophyllales","canonical_form":"Caryophyllales"},{"id":29,"lid":29,"rank":5,"name":"Amaranthaceae","canonical_form":"Amaranthaceae"}],"group":{"id":10,"name":"Plants","groupOrder":0},"parentName":null,"position":"Clean","speciesId":null},{"id":127,"name":"Celosia","canonicalForm":"Celosia","italicisedForm":"<i>Celosia<\u002fi>","rank":"Genus","nameStatus":"accepted","sourceDatabase":"","defaultHierarchy":[{"id":1,"lid":127,"rank":0,"name":"Plantae","canonical_form":"Plantae"},{"id":2,"lid":127,"rank":1,"name":"Tracheophyta","canonical_form":"Tracheophyta"},{"id":3,"lid":127,"rank":2,"name":"Magnoliopsida","canonical_form":"Magnoliopsida"},{"id":28,"lid":127,"rank":3,"name":"Caryophyllales","canonical_form":"Caryophyllales"},{"id":29,"lid":127,"rank":5,"name":"Amaranthaceae","canonical_form":"Amaranthaceae"},{"id":127,"lid":127,"rank":7,"name":"Celosia","canonical_form":"Celosia"}],"group":{"id":10,"name":"Plants","groupOrder":0},"parentName":null,"position":"Clean","speciesId":null},{"id":129,"name":"Celosia trigyna L.","canonicalForm":"Celosia trigyna","italicisedForm":"<i>Celosia trigyna <\u002fi>L. ","rank":"Species","nameStatus":"accepted","sourceDatabase":"Thomas Le_bourgeois","defaultHierarchy":[{"id":1,"lid":129,"rank":0,"name":"Plantae","canonical_form":"Plantae"},{"id":2,"lid":129,"rank":1,"name":"Tracheophyta","canonical_form":"Tracheophyta"},{"id":3,"lid":129,"rank":2,"name":"Magnoliopsida","canonical_form":"Magnoliopsida"},{"id":28,"lid":129,"rank":3,"name":"Caryophyllales","canonical_form":"Caryophyllales"},{"id":29,"lid":129,"rank":5,"name":"Amaranthaceae","canonical_form":"Amaranthaceae"},{"id":127,"lid":129,"rank":7,"name":"Celosia","canonical_form":"Celosia"},{"id":129,"lid":129,"rank":9,"name":"Celosia trigyna L.","canonical_form":"Celosia trigyna"}],"group":{"id":10,"name":"Plants","groupOrder":0},"parentName":null,"position":"Clean","speciesId":52}]}],"synonyms":[{"id":7118,"name":"Achyranthes fasciculata Ehrenb. ex Schweinf. [Invalid]","canonicalForm":"Achyranthes fasciculata","italicisedForm":"<i>Achyranthes fasciculata <\u002fi>Ehrenb.<i> ex <\u002fi>Schweinf.<i> [Invalid]<\u002fi>","rank":"Species","nameStatus":"synonym","sourceDatabase":"","defaultHierarchy":null,"group":{"id":10,"name":"Plants","groupOrder":0},"parentName":null,"position":"Raw","speciesId":null},{"id":7119,"name":"Celosia acroprosoides Hochst. ex Oliv.","canonicalForm":"Celosia acroprosoides","italicisedForm":"<i>Celosia acroprosoides <\u002fi>Hochst.<i> ex <\u002fi>Oliv. ","rank":"Species","nameStatus":"synonym","sourceDatabase":"","defaultHierarchy":null,"group":{"id":10,"name":"Plants","groupOrder":0},"parentName":null,"position":"Raw","speciesId":null},{"id":7120,"name":"Celosia adoensis Hochst. ex A.Rich.","canonicalForm":"Celosia adoensis","italicisedForm":"<i>Celosia adoensis <\u002fi>Hochst.<i> ex <\u002fi>A.Rich. ","rank":"Species","nameStatus":"synonym","sourceDatabase":"","defaultHierarchy":null,"group":{"id":10,"name":"Plants","groupOrder":0},"parentName":null,"position":"Raw","speciesId":null},{"id":7121,"name":"Celosia digyna Suess.","canonicalForm":"Celosia digyna","italicisedForm":"<i>Celosia digyna <\u002fi>Suess. ","rank":"Species","nameStatus":"synonym","sourceDatabase":"","defaultHierarchy":null,"group":{"id":10,"name":"Plants","groupOrder":0},"parentName":null,"position":"Raw","speciesId":null},{"id":7122,"name":"Celosia laxa Schumach. & Thonn.","canonicalForm":"Celosia laxa","italicisedForm":"<i>Celosia laxa <\u002fi>Schumach.<i> & <\u002fi>Thonn. ","rank":"Species","nameStatus":"synonym","sourceDatabase":"","defaultHierarchy":null,"group":{"id":10,"name":"Plants","groupOrder":0},"parentName":null,"position":"Raw","speciesId":null},{"id":7123,"name":"Celosia melanocarpos Poir.","canonicalForm":"Celosia melanocarpos","italicisedForm":"<i>Celosia melanocarpos <\u002fi>Poir. ","rank":"Species","nameStatus":"synonym","sourceDatabase":"","defaultHierarchy":null,"group":{"id":10,"name":"Plants","groupOrder":0},"parentName":null,"position":"Raw","speciesId":null},{"id":7124,"name":"Celosia minutiflora Baker","canonicalForm":"Celosia minutiflora","italicisedForm":"<i>Celosia minutiflora <\u002fi>Baker ","rank":"Species","nameStatus":"synonym","sourceDatabase":"","defaultHierarchy":null,"group":{"id":10,"name":"Plants","groupOrder":0},"parentName":null,"position":"Raw","speciesId":null},{"id":7125,"name":"Celosia semperflorens Baker","canonicalForm":"Celosia semperflorens","italicisedForm":"<i>Celosia semperflorens <\u002fi>Baker ","rank":"Species","nameStatus":"synonym","sourceDatabase":"","defaultHierarchy":null,"group":{"id":10,"name":"Plants","groupOrder":0},"parentName":null,"position":"Raw","speciesId":null},{"id":1524,"name":"Celosia trigyna var. adoensis Moq.","canonicalForm":"Celosia trigyna adoensis","italicisedForm":"<i>Celosia trigyna <\u002fi>var.<i> adoensis <\u002fi>Moq. ","rank":"Infraspecies","nameStatus":"synonym","sourceDatabase":"","defaultHierarchy":null,"group":{"id":10,"name":"Plants","groupOrder":0},"parentName":null,"position":"Working","speciesId":null},{"id":1525,"name":"Celosia trigyna var. fasciculiflora Moq.","canonicalForm":"Celosia trigyna fasciculiflora","italicisedForm":"<i>Celosia trigyna <\u002fi>var.<i> fasciculiflora <\u002fi>Moq. ","rank":"Infraspecies","nameStatus":"synonym","sourceDatabase":"","defaultHierarchy":null,"group":{"id":10,"name":"Plants","groupOrder":0},"parentName":null,"position":"Working","speciesId":null},{"id":7126,"name":"Celosia trigyna var. longistyla subvars. convexa Suess. et brevifilamentosa Suess.","canonicalForm":"Celosia trigyna longistyla","italicisedForm":"<i>Celosia trigyna <\u002fi>var.<i> longistyla <\u002fi>subvars.<i> convexa Suess. et brevifilamentosa Suess.<\u002fi>","rank":"Species","nameStatus":"synonym","sourceDatabase":"","defaultHierarchy":null,"group":{"id":10,"name":"Plants","groupOrder":0},"parentName":null,"position":"Raw","speciesId":null},{"id":7127,"name":"Celosia trigyna var. pauciflora Moq.","canonicalForm":"Celosia trigyna pauciflora","italicisedForm":"<i>Celosia trigyna <\u002fi>var.<i> pauciflora <\u002fi>Moq. ","rank":"Species","nameStatus":"synonym","sourceDatabase":"","defaultHierarchy":null,"group":{"id":10,"name":"Plants","groupOrder":0},"parentName":null,"position":"Raw","speciesId":null},{"id":1526,"name":"Celosia triloba E. Mey. ex Meisn.","canonicalForm":"Celosia triloba","italicisedForm":"<i>Celosia triloba <\u002fi>E. Mey.<i> ex <\u002fi>Meisn. ","rank":"Species","nameStatus":"synonym","sourceDatabase":"","defaultHierarchy":null,"group":{"id":10,"name":"Plants","groupOrder":0},"parentName":null,"position":"Working","speciesId":null},{"id":7128,"name":"Celosia triloba E.Mey. ex Meisn.","canonicalForm":"Celosia triloba","italicisedForm":"<i>Celosia triloba <\u002fi>E.Mey.<i> ex <\u002fi>Meisn. ","rank":"Species","nameStatus":"synonym","sourceDatabase":"","defaultHierarchy":null,"group":{"id":10,"name":"Plants","groupOrder":0},"parentName":null,"position":"Raw","speciesId":null},{"id":7129,"name":"Lestibudesia trigyna (L.) R.Br.","canonicalForm":"Lestibudesia trigyna","italicisedForm":"<i>Lestibudesia trigyna (<\u002fi>L.<i>) <\u002fi>R.Br. ","rank":"Species","nameStatus":"synonym","sourceDatabase":"","defaultHierarchy":null,"group":{"id":10,"name":"Plants","groupOrder":0},"parentName":null,"position":"Raw","speciesId":null}],"common_names":[{"id":315,"name":"Fotsimbarinakoho","taxonConcept":{"id":129},"isContributor":false,"language":{"id":486,"name":"Malgache","threeLetterCode":"620","twoLetterCode":null}}],"group":{"id":10,"name":"Plants","groupOrder":0},"habitat":null,"createdOn":"2014-09-24T17:04:53Z","lastRevised":"2016-07-05T09:36:36Z","thumbnail":"http://portal.wikwio.org/biodiv/img//Celosia trigyna/464_th1.jpg","notes":"<h6>Biological Type<\u002fh6><p>broadleaf<\u002fp><h6>Code<\u002fh6><p>CEOTR<\u002fp><h6>Habitat<\u002fh6><p>terrestrial<\u002fp><h6>Life Form<\u002fh6><p>annual<\u002fp>","summary":"<h6>Biological Type<\u002fh6><p>broadleaf<\u002fp><h6>Code<\u002fh6><p>CEOTR<\u002fp><h6>Habitat<\u002fh6><p>terrestrial<\u002fp><h6>Life Form<\u002fh6><p>annual<\u002fp>","fields":[{"id":457,"field":{"concept":"Overview","category":"Summary","description":"A general summary, with any kind of information about the taxon. Its main goal is summarize the most relevant or attractive characteristics of this taxon to the general public.","language":{"id":123,"name":"English","threeLetterCode":"eng","twoLetterCode":"en"}},"text":"<h6>Biological Type<\u002fh6><p>broadleaf<\u002fp><h6>Code<\u002fh6><p>CEOTR<\u002fp><h6>Habitat<\u002fh6><p>terrestrial<\u002fp><h6>Life Form<\u002fh6><p>annual<\u002fp>","dateCreated":"2014-09-24T17:06:50Z","lastUpdated":"2014-09-24T17:06:50Z","licenses":[{"name":"CC BY-SA","url":"http://creativecommons.org/licenses/by-sa/3.0/ "}],"audienceTypes":[],"resources":[],"references":[],"contributors":[{"id":3,"name":"WIKWIO Portal","icon":"http://portal.wikwio.org/biodiv/users//23ff2afb-1bb8-45e2-a351-263413cbf81d/resources/971_th1.jpg"}],"attributors":[{"name":"Wikwio project"}],"uploader":{"id":53,"name":"Thomas Vattakaven","icon":"http://portal.wikwio.org/biodiv/users//3eb87510-237c-40c1-958a-12adad22db7c/resources/73_th1.jpg"},"uploadTime":1411578410486,"language":{"id":123,"name":"English","threeLetterCode":"eng","twoLetterCode":"en"},"rating":0},{"id":63370,"field":{"concept":"Overview","category":"Brief","description":"A general description, with any kind of information about the taxon. Its main goal is summarize the most relevant or attractive characteristics of this taxon to the general public.","language":{"id":123,"name":"English","threeLetterCode":"eng","twoLetterCode":"en"}},"text":"<p>\n\t&nbsp;a<\u002fp>\n<h6 style=\"margin-top:7.5pt;margin-right:0in;margin-bottom:7.5pt;margin-left:\n0in;line-height:15.0pt\">\n\t<b><span style=\"font-size: 10.5pt; font-family: Helvetica, sans-serif; color: rgb(51, 51, 51);\">Code<o:p><\u002fo:p><\u002fspan><\u002fb><\u002fh6>\n<p style=\"margin-top:0in;margin-right:0in;margin-bottom:7.5pt;margin-left:0in;\nline-height:15.0pt\">\n\t<span style=\"font-size:10.5pt;font-family:&quot;Helvetica&quot;,sans-serif;\ncolor:#333333\">CEOTR<o:p><\u002fo:p><\u002fspan><\u002fp>\n<h6 style=\"margin-top:7.5pt;margin-right:0in;margin-bottom:7.5pt;margin-left:\n0in;line-height:15.0pt\">\n\t<b><span style=\"font-size: 10.5pt; font-family: Helvetica, sans-serif; color: rgb(51, 51, 51);\">Biological Type<o:p><\u002fo:p><\u002fspan><\u002fb><\u002fh6>\n<p style=\"margin-top:0in;margin-right:0in;margin-bottom:7.5pt;margin-left:0in;\nline-height:15.0pt\">\n\t<span style=\"font-size:10.5pt;font-family:&quot;Helvetica&quot;,sans-serif;\ncolor:#333333\">Broadleaf<o:p><\u002fo:p><\u002fspan><\u002fp>\n<h6 style=\"margin-top:7.5pt;margin-right:0in;margin-bottom:7.5pt;margin-left:\n0in;line-height:15.0pt\">\n\t<b><span style=\"font-size: 10.5pt; font-family: Helvetica, sans-serif; color: rgb(51, 51, 51);\">Life Form<o:p><\u002fo:p><\u002fspan><\u002fb><\u002fh6>\n<p style=\"margin-top:0in;margin-right:0in;margin-bottom:7.5pt;margin-left:0in;\nline-height:15.0pt\">\n\t<span style=\"font-size:10.5pt;font-family:&quot;Helvetica&quot;,sans-serif;\ncolor:#333333\">Annual<o:p><\u002fo:p><\u002fspan><\u002fp>\n<h6 style=\"margin-top:7.5pt;margin-right:0in;margin-bottom:7.5pt;margin-left:\n0in;line-height:15.0pt\">\n\t<b><span style=\"font-size: 10.5pt; font-family: Helvetica, sans-serif; color: rgb(51, 51, 51);\">Habitat<o:p><\u002fo:p><\u002fspan><\u002fb><\u002fh6>\n<p style=\"margin-top:0in;margin-right:0in;margin-bottom:7.5pt;margin-left:0in;\nline-height:15.0pt\">\n\t<span style=\"font-size:10.5pt;font-family:&quot;Helvetica&quot;,sans-serif;\ncolor:#333333\">Terrestrial<o:p><\u002fo:p><\u002fspan><\u002fp>\n","dateCreated":"2016-05-17T05:15:38Z","lastUpdated":"2016-05-17T05:15:38Z","licenses":[{"name":"CC BY","url":"http://creativecommons.org/licenses/by/3.0/"}],"audienceTypes":[{"enumType":"species.SpeciesField$AudienceType","name":"EXPERT_USERS"}],"resources":[],"references":[],"contributors":[{"id":391,"name":"Lovena Nowbut","icon":"http://portal.wikwio.org/biodiv/users/user_large.png"}],"attributors":[{"name":"WIKWIO USER"}],"uploader":{"id":391,"name":"Lovena Nowbut","icon":"http://portal.wikwio.org/biodiv/users/user_large.png"},"uploadTime":1463462138363,"language":{"id":123,"name":"English","threeLetterCode":"eng","twoLetterCode":"en"},"rating":0},{"id":63373,"field":{"concept":"Overview","category":"Diagnostic","subCategory":"Description","description":"A textual diagnostic description of the species that is not necessarily structured.","language":{"id":123,"name":"English","threeLetterCode":"eng","twoLetterCode":"en"}},"text":"<p>\n\t<strong>Description Global<\u002fstrong><\u002fp>\n&nbsp;<br />\n<em>Celosia trigyna<\u002fem> is an upright herb, which can reach up to 1 m high, with an angular and slightly branched stem. The leaves are simple, alternate, with long-stalked triangular ovate lamina. At the base of the petioles are 2 sickled foliaceous structures, characteristics of this species. The flowers are very small and are assembled in discontinuous white balls at the ends of the branches. The fruits are small globular capsules<br />\n&nbsp;<br />\n<strong>Cotyledons<\u002fstrong><br />\n&nbsp;<br />\nThe cotyledons are lanceolate to elliptical. They are slightly stalked and are 10 mm long and 3 mm wide<br />\n&nbsp;<br />\n<strong>First Leaves<\u002fstrong><br />\n&nbsp;<br />\nThe first leaves are simple and alternate. They are oval and held by a petiole almost as long as the leaf blade.<br />\n&nbsp;<br />\n<strong>Growth habit<\u002fstrong><br />\n&nbsp;<br />\nErect plant, more or less branched. It is 40 to 100 cm high.<br />\n&nbsp;<br />\n<strong>Underground System<\u002fstrong><br />\n&nbsp;<br />\nThe plant has a taproot system.<br />\n&nbsp;<br />\n<strong>Stem<\u002fstrong><br />\n&nbsp;<br />\nThe stem is full and very angular, generally having five very marked angles. It is glabrous.<br />\n&nbsp;<br />\n<strong>Leaf<\u002fstrong><br />\n&nbsp;<br />\nThe leaves are simple and alternate. They are carried by a long stalk of 3 to 8 cm, almost as long as the leaf blade. The lamina is oval to nearly triangular, 5 to 8 cm long and 3 to 6 cm wide. The base is wedged and sometimes almost perpendicular to the petiole. The top is wedged. Both sides are glabrous. The margin is entire, finely scabrous. They are marked by 6 to 10 lateral ribs. A very remarkable feature of this species is the presence of 2 sickled foliaceous structures, 10-15 mm long at the base of the leaf, surrounding the stem. These foliaceous structures, which resemble to stipules, correspond to the first leaves of axillary branches more or less developed. This character appears as from the fourth or fifth leaf.<br />\n&nbsp;<br />\n<strong>Inflorescence<\u002fstrong><br />\n&nbsp;<br />\nThe inflorescence is composed of clusters of tiny white flowers. These clusters are themselves arranged in terminal and discontinuous spikes discontinuous, more or less branched.<br />\n&nbsp;<br />\n<strong>Flower<\u002fstrong><br />\n&nbsp;<br />\nThe flowers are formed by 5 elliptic membranous structures, white in color and measuring 1.5 to 2 mm long. Inside these parts are 5 pink stamens and a globular ovary surmounted by a very short three branched style.<br />\n&nbsp;<br />\n<strong>Fruit<\u002fstrong><br />\n&nbsp;<br />\nThe fruit is a dehiscent capsule, globose. It measures 1.5 to 2 mm high and 1.2 to 1.5 mm wide. The opening is done by detachment of the upper half of the capsule. This is topped by the short trifid style 0.3 mm high. One capsule contains 4 to 8 seeds.<br />\n&nbsp;<br />\n<strong>Seed<\u002fstrong><br />\n&nbsp;<br />\nThe seed is kidney-shaped. It measures 0.8 mm in diameter and 0.2 mm thick. The seed coat is shiny black<br />\n","dateCreated":"2016-05-17T05:17:23Z","lastUpdated":"2016-05-17T05:17:23Z","licenses":[{"name":"CC BY","url":"http://creativecommons.org/licenses/by/3.0/"}],"audienceTypes":[{"enumType":"species.SpeciesField$AudienceType","name":"EXPERT_USERS"}],"resources":[],"references":[],"contributors":[{"id":391,"name":"Lovena Nowbut","icon":"http://portal.wikwio.org/biodiv/users/user_large.png"}],"attributors":[{"name":"WIKWIO USER"}],"uploader":{"id":391,"name":"Lovena Nowbut","icon":"http://portal.wikwio.org/biodiv/users/user_large.png"},"uploadTime":1463462243068,"language":{"id":123,"name":"English","threeLetterCode":"eng","twoLetterCode":"en"},"rating":0},{"id":458,"field":{"concept":"Nomenclature and Classification","category":"Taxon Record Name","subCategory":"Scientific Name","description":"The full name of the lowest level taxon to which the organism has been identified in the most recent accepted determination, specified as precisely as possible, including name of author, year of authorship, sensu or sec. (according to or following) author, and indication of uncertainty. Conceptually equivalent to a full taxonomic identification as given by the identifier (verbatim). Does not include the identifier name or date of identification","language":{"id":123,"name":"English","threeLetterCode":"eng","twoLetterCode":"en"}},"text":"Celosia trigyna L.","dateCreated":"2014-09-24T17:06:50Z","lastUpdated":"2014-09-24T17:06:50Z","licenses":[{"name":"CC BY-SA","url":"http://creativecommons.org/licenses/by-sa/3.0/ "}],"audienceTypes":[],"resources":[],"references":[],"contributors":[{"id":3,"name":"WIKWIO Portal","icon":"http://portal.wikwio.org/biodiv/users//23ff2afb-1bb8-45e2-a351-263413cbf81d/resources/971_th1.jpg"}],"attributors":[{"name":"Wikwio project"}],"uploader":{"id":53,"name":"Thomas Vattakaven","icon":"http://portal.wikwio.org/biodiv/users//3eb87510-237c-40c1-958a-12adad22db7c/resources/73_th1.jpg"},"uploadTime":1411578410486,"language":{"id":123,"name":"English","threeLetterCode":"eng","twoLetterCode":"en"},"rating":0},{"id":63375,"field":{"concept":"Natural History","category":"Cyclicity","description":"Describes biorhythms - those states or conditions characterised by regular repetition in time, whether on the scale of seconds, hours, days, or seasons. It could also cover phenomena such as \"plant flowering\" or \"chewing rates\". Life cycles are treated in the field for Life Cycle. Seasonal migration and reproduction are usually treated separately.","language":{"id":123,"name":"English","threeLetterCode":"eng","twoLetterCode":"en"}},"text":"<p>\n\t<strong>Northern Cameroon<\u002fstrong>: <em>C. trigyna<\u002fem> is uncommon in early rainy season. Germination takes place in June when the rain becomes heavy and regular. The germination takes 1 to 2 weeks, but may be delayed by tillage at the start of cultivation (plowing, weeding). Flowering starts in August and fruiting occurs three weeks later. Fruiting continues until the plant dries out at the start of the dry season (November). A full development cycle lasts three months when germination takes place in June and only 3-4 weeks old when germination takes place at the end of the crop cycle. The flower development is linked to shortening of day length.<br />\n\t<strong>Madagascar<\u002fstrong>: <em>C. trigyna<\u002fem> occurs in the middle and at the end of the cycle of rainfed crops.<\u002fp>\n","dateCreated":"2016-05-17T05:18:23Z","lastUpdated":"2016-05-17T05:18:23Z","licenses":[{"name":"CC BY","url":"http://creativecommons.org/licenses/by/3.0/"}],"audienceTypes":[{"enumType":"species.SpeciesField$AudienceType","name":"EXPERT_USERS"}],"resources":[],"references":[],"contributors":[{"id":391,"name":"Lovena Nowbut","icon":"http://portal.wikwio.org/biodiv/users/user_large.png"}],"attributors":[{"name":"WIKWIO USER"}],"uploader":{"id":391,"name":"Lovena Nowbut","icon":"http://portal.wikwio.org/biodiv/users/user_large.png"},"uploadTime":1463462303426,"language":{"id":123,"name":"English","threeLetterCode":"eng","twoLetterCode":"en"},"rating":0},{"id":63379,"field":{"concept":"Natural History","category":"Reproduction","description":"Describes reproductive physiology and behavior, including mating and life history variables. Includes cues, strategies, restraints, rates.","language":{"id":123,"name":"English","threeLetterCode":"eng","twoLetterCode":"en"}},"text":"<em>C. trigyna<\u002fem> is an annual species. It multiplies only by seed. These are spread by wind and water and soil working tools.<br />\n<p>\n<\u002fp>\n","dateCreated":"2016-05-17T05:20:53Z","lastUpdated":"2016-05-17T05:20:53Z","licenses":[{"name":"CC BY","url":"http://creativecommons.org/licenses/by/3.0/"}],"audienceTypes":[{"enumType":"species.SpeciesField$AudienceType","name":"EXPERT_USERS"}],"resources":[],"references":[],"contributors":[{"id":391,"name":"Lovena Nowbut","icon":"http://portal.wikwio.org/biodiv/users/user_large.png"}],"attributors":[{"name":"WIKWIO USER"}],"uploader":{"id":391,"name":"Lovena Nowbut","icon":"http://portal.wikwio.org/biodiv/users/user_large.png"},"uploadTime":1463462453204,"language":{"id":123,"name":"English","threeLetterCode":"eng","twoLetterCode":"en"},"rating":0},{"id":63377,"field":{"concept":"Natural History","category":"Look Alikes","description":"Other taxa that this taxon may be confused with, and characters useful for their differentiation. Useful for identification and comparison. Common in invasive species communities.","language":{"id":123,"name":"English","threeLetterCode":"eng","twoLetterCode":"en"}},"text":"<table border=\"1\" cellpadding=\"1\" cellspacing=\"1\" height=\"204\" style=\"max-width: 100%; border-collapse: collapse; border-spacing: 0px; color: rgb(51, 51, 51); font-family: 'Helvetica Neue', Helvetica, Arial, sans-serif; line-height: 20px; background-color: rgb(255, 255, 255);\" width=\"610\">\n\t<caption>\n\t\t<strong>Comparison of Celosia<\u002fstrong><\u002fcaption>\n\t<thead>\n\t\t<tr>\n\t\t\t<th scope=\"col\">\n\t\t\t<\u002fth>\n\t\t\t<th scope=\"col\" style=\"text-align: center; background-color: rgb(102, 255, 255);\">\n\t\t\t\tC. trigyna<\u002fth>\n\t\t\t<th scope=\"col\" style=\"text-align: center; background-color: rgb(102, 255, 255);\">\n\t\t\t\tC. argentea<\u002fth>\n\t\t<\u002ftr>\n\t<\u002fthead>\n\t<tbody>\n\t\t<tr>\n\t\t\t<td style=\"background-color: rgb(255, 255, 102);\">\n\t\t\t\t<strong>petiole<\u002fstrong><\u002ftd>\n\t\t\t<td style=\"text-align: center;\">\n\t\t\t\tlong<\u002ftd>\n\t\t\t<td style=\"text-align: center;\">\n\t\t\t\tShort<\u002ftd>\n\t\t<\u002ftr>\n\t\t<tr>\n\t\t\t<td style=\"background-color: rgb(255, 255, 102);\">\n\t\t\t\t<strong>Shape of leaf blade<\u002fstrong><\u002ftd>\n\t\t\t<td style=\"text-align: center;\">\n\t\t\t\toval to nearly triangular<\u002ftd>\n\t\t\t<td style=\"text-align: center;\">\n\t\t\t\tlanceolate to linear&nbsp;<\u002ftd>\n\t\t<\u002ftr>\n\t\t<tr>\n\t\t\t<td style=\"background-color: rgb(255, 255, 102);\">\n\t\t\t\t<strong>Base of leaf blade<\u002fstrong><\u002ftd>\n\t\t\t<td style=\"text-align: center;\">\n\t\t\t\tsometimes almost perpendicular to the petiole<\u002ftd>\n\t\t\t<td style=\"text-align: center;\">\n\t\t\t\tattenuated<\u002ftd>\n\t\t<\u002ftr>\n\t\t<tr>\n\t\t\t<td style=\"background-color: rgb(255, 255, 102);\">\n\t\t\t\t<strong>inflorescence (Shape)<\u002fstrong><\u002ftd>\n\t\t\t<td style=\"text-align: center;\">\n\t\t\t\tclusters of very small flowers&nbsp;<\u002ftd>\n\t\t\t<td style=\"text-align: center;\">\n\t\t\t\tdense terminal spikes&nbsp;<\u002ftd>\n\t\t<\u002ftr>\n\t\t<tr>\n\t\t\t<td style=\"background-color: rgb(255, 255, 102);\">\n\t\t\t\t<strong>inflorescence (color)<\u002fstrong><\u002ftd>\n\t\t\t<td style=\"text-align: center;\">\n\t\t\t\tWhite&nbsp;<\u002ftd>\n\t\t\t<td style=\"text-align: center;\">\n\t\t\t\tPinkish white to bright pink<\u002ftd>\n\t\t<\u002ftr>\n\t<\u002ftbody>\n<\u002ftable>\n<p>\n<\u002fp>\n","dateCreated":"2016-05-17T05:19:57Z","lastUpdated":"2016-05-17T05:19:57Z","licenses":[{"name":"CC BY","url":"http://creativecommons.org/licenses/by/3.0/"}],"audienceTypes":[{"enumType":"species.SpeciesField$AudienceType","name":"EXPERT_USERS"}],"resources":[],"references":[],"contributors":[{"id":391,"name":"Lovena Nowbut","icon":"http://portal.wikwio.org/biodiv/users/user_large.png"}],"attributors":[{"name":"WIKWIO USER"}],"uploader":{"id":391,"name":"Lovena Nowbut","icon":"http://portal.wikwio.org/biodiv/users/user_large.png"},"uploadTime":1463462397459,"language":{"id":123,"name":"English","threeLetterCode":"eng","twoLetterCode":"en"},"rating":0},{"id":63381,"field":{"concept":"Natural History","category":"Ecology","description":"Relations that living organisms have with respect to each other and their natural environment. Variables of interest to ecologists include the composition, distribution, amount (biomass), number, and changing states of organisms within and among ecosystems.","language":{"id":123,"name":"English","threeLetterCode":"eng","twoLetterCode":"en"}},"text":"<strong>Northern Cameroon<\u002fstrong>: <em>C. trigyna<\u002fem> is a very common weed of annual crops in regions of Sudano-Sahelian climate Sudanese whose annual rainfall exceeds 800 mm. It is then present in 30% of the plots. It has no significant preference for the soil type and grows both in both ferruginous degraded soil and on planosol. In the Sudano-Sahelian region, it is very rare and only grows on high water retention soil. It is a weed characteristic of cultivated plots for many years and subject to semi-intensive crop management (animal traction, mineral fertilizer) or intensive (animal traction, strong mineral fertilizers and repeated use of herbicides pre- lifting of cotton). It belongs to the floristic procession of <em>Commelina benghalensis<\u002fem>. Although common in Sudan zone, it is rarely abundant.<br />\n<strong>Madagascar<\u002fstrong>: The species grows on ferralitic soils, ferruginous soils and fertile alluvium in quite sunny areas. It is a weed of rainfed crops (corn, cotton, peanuts) in semi-arid and sub-humid areas, up to 1200 m altitude in semi-intensive culture systems without fertilization. The concerned agro-ecological zones in Madagascar are the Southwest, West, Northwest and Highlands.<br />\n<strong>Mauritius<\u002fstrong>: absent.<br />\n<strong>Reunion<\u002fstrong>: absent.<br />\n<strong>Seychelles:<\u002fstrong> absent<br />\n&nbsp;<br />\n<p>\n<\u002fp>\n","dateCreated":"2016-05-17T05:22:43Z","lastUpdated":"2016-05-17T05:22:43Z","licenses":[{"name":"CC BY","url":"http://creativecommons.org/licenses/by/3.0/"}],"audienceTypes":[{"enumType":"species.SpeciesField$AudienceType","name":"EXPERT_USERS"}],"resources":[],"references":[],"contributors":[{"id":391,"name":"Lovena Nowbut","icon":"http://portal.wikwio.org/biodiv/users/user_large.png"}],"attributors":[{"name":"WIKWIO USER"}],"uploader":{"id":391,"name":"Lovena Nowbut","icon":"http://portal.wikwio.org/biodiv/users/user_large.png"},"uploadTime":1463462563773,"language":{"id":123,"name":"English","threeLetterCode":"eng","twoLetterCode":"en"},"rating":0},{"id":63383,"field":{"concept":"Habitat and Distribution","category":"Distribution","subCategory":"Description","description":"Enumerates geographic entities where the taxon lives. Covers ranges, e.g., a global range, or a narrower one; may be biogeographical, political or other (e.g., managed areas like conservencies); endemism; native or exotic. Does not include altitudinal distribution, which is covered under Habitat.","language":{"id":123,"name":"English","threeLetterCode":"eng","twoLetterCode":"en"}},"text":"<strong>Worldwide distribution<\u002fstrong><br />\n&nbsp;<br />\nThis species is widespread in Africa, and also in the Arabian Peninsula and Madagascar.<br />\n<p>\n<\u002fp>\n","dateCreated":"2016-05-17T05:24:01Z","lastUpdated":"2016-05-17T05:24:01Z","licenses":[{"name":"CC BY","url":"http://creativecommons.org/licenses/by/3.0/"}],"audienceTypes":[{"enumType":"species.SpeciesField$AudienceType","name":"EXPERT_USERS"}],"resources":[],"references":[],"contributors":[{"id":391,"name":"Lovena Nowbut","icon":"http://portal.wikwio.org/biodiv/users/user_large.png"}],"attributors":[{"name":"WIKWIO USER"}],"uploader":{"id":391,"name":"Lovena Nowbut","icon":"http://portal.wikwio.org/biodiv/users/user_large.png"},"uploadTime":1463462641399,"language":{"id":123,"name":"English","threeLetterCode":"eng","twoLetterCode":"en"},"rating":0},{"id":63385,"field":{"concept":"Demography and Conservation","category":"Risk Statement","description":"Negative impacts on humans, communities. Includes Invasiveness. [This may also include impacts on ecosystems should the organism decline or be extirpated]","language":{"id":123,"name":"English","threeLetterCode":"eng","twoLetterCode":"en"}},"text":"<strong>Local harmfulness<\u002fstrong><br />\n&nbsp;<br />\n<strong>Madagascar<\u002fstrong>: <em>C. trigyna<\u002fem> is a weed of medium frequency and of generally low to medium abundance in rainfed cultivation: rainfed rice, cotton, corn. At the end of the cycle, it can be inconvenient for the harvesting operations due to its vegetative development.<br />\n<strong>Mauritius<\u002fstrong>: absent.<br />\n<strong>Reunion<\u002fstrong>: absent.<br />\n<strong>Seychelles<\u002fstrong>: absent&nbsp;","dateCreated":"2016-05-17T05:25:17Z","lastUpdated":"2016-05-17T05:25:17Z","licenses":[{"name":"CC BY","url":"http://creativecommons.org/licenses/by/3.0/"}],"audienceTypes":[{"enumType":"species.SpeciesField$AudienceType","name":"EXPERT_USERS"}],"resources":[],"references":[],"contributors":[{"id":391,"name":"Lovena Nowbut","icon":"http://portal.wikwio.org/biodiv/users/user_large.png"}],"attributors":[{"name":"WIKWIO USER"}],"uploader":{"id":391,"name":"Lovena Nowbut","icon":"http://portal.wikwio.org/biodiv/users/user_large.png"},"uploadTime":1463462717908,"language":{"id":123,"name":"English","threeLetterCode":"eng","twoLetterCode":"en"},"rating":0},{"id":63387,"field":{"concept":"Uses and Management","category":"Uses","description":"Known or potential benefits of the species for humans, at a direct economic level, as instruments of education, prospecting, eco-tourism, etc. It includes published material or suggestions from the author or others. In any event, the source must be explicitly quoted. Can include ecosystem services. However, benefits to ecosystems not specific to humans are best treated under Risk statement (what happens when the organism is removed)","language":{"id":123,"name":"English","threeLetterCode":"eng","twoLetterCode":"en"}},"text":"<p>\n\t<strong>Food<\u002fstrong>: The leaves with the young stems are eaten as vegetables.<\u002fp>\n<strong>Livestock feed:<\u002fstrong> The whole plant can be used as forage, in particular for rabbits.<br />\n&nbsp;<br />\n<strong>Medicinal<\u002fstrong>: <em>C. trigyna<\u002fem> is used in traditional medicine against cardiac pain. Anti inflammatory and anti oxidant activities of the extracts from the plant are proven.<br />\n","dateCreated":"2016-05-17T05:27:03Z","lastUpdated":"2016-05-17T05:27:03Z","licenses":[{"name":"CC BY","url":"http://creativecommons.org/licenses/by/3.0/"}],"audienceTypes":[{"enumType":"species.SpeciesField$AudienceType","name":"EXPERT_USERS"}],"resources":[],"references":[],"contributors":[{"id":391,"name":"Lovena Nowbut","icon":"http://portal.wikwio.org/biodiv/users/user_large.png"}],"attributors":[{"name":"WIKWIO USER"}],"uploader":{"id":391,"name":"Lovena Nowbut","icon":"http://portal.wikwio.org/biodiv/users/user_large.png"},"uploadTime":1463462823525,"language":{"id":123,"name":"English","threeLetterCode":"eng","twoLetterCode":"en"},"rating":0},{"id":63389,"field":{"concept":"Uses and Management","category":"Management","description":"Describes techniques and goals used in management of species - breeding and cultivation, control etc. May include management relative to a piece of legislation, e.g., a CITES list.","language":{"id":123,"name":"English","threeLetterCode":"eng","twoLetterCode":"en"}},"text":"<strong>Local Management<\u002fstrong><br />\n<br />\n<strong>Madagascar<\u002fstrong>: In Madagascar manual weeding is practically the only way used to fight against <em>C. trigyna<\u002fem>.<br />\n<p>\n<\u002fp>\n","dateCreated":"2016-05-17T05:28:08Z","lastUpdated":"2016-05-17T05:28:08Z","licenses":[{"name":"CC BY","url":"http://creativecommons.org/licenses/by/3.0/"}],"audienceTypes":[{"enumType":"species.SpeciesField$AudienceType","name":"EXPERT_USERS"}],"resources":[],"references":[],"contributors":[{"id":391,"name":"Lovena Nowbut","icon":"http://portal.wikwio.org/biodiv/users/user_large.png"}],"attributors":[{"name":"WIKWIO USER"}],"uploader":{"id":391,"name":"Lovena Nowbut","icon":"http://portal.wikwio.org/biodiv/users/user_large.png"},"uploadTime":1463462888827,"language":{"id":123,"name":"English","threeLetterCode":"eng","twoLetterCode":"en"},"rating":0},{"id":3164,"field":{"concept":"Généralités","category":"Summary","description":"Résumé général du taxon mettant en évidence les principales caractériqtiques du taxon pour le grand public.","language":{"id":137,"name":"French","threeLetterCode":"fre","twoLetterCode":"fr"}},"text":"<h6>Description Globale<\u002fh6><p>Celosia trigyna est une plante herbacée dressée pouvant atteindre 1 m de hauteur, à tige anguleuse peu ramifiée. Les feuilles sont simples, alternes, longuement pétiolées à limbe ovale triangulaire. A la base des pétioles se trouvent de 2 pièces foliacées falciformes caractéristiques de cette espèce. Les fleurs sont très petites et assemblées en boules blanches discontinues à l'extrémité des rameaux. Les fruits sont de petites capsules globuleuses<\u002fp>","dateCreated":"2015-03-19T11:10:15Z","lastUpdated":"2015-03-19T11:10:15Z","licenses":[{"name":"CC BY-SA","url":"http://creativecommons.org/licenses/by-sa/3.0/ "}],"audienceTypes":[],"resources":[],"references":[],"contributors":[{"id":3,"name":"WIKWIO Portal","icon":"http://portal.wikwio.org/biodiv/users//23ff2afb-1bb8-45e2-a351-263413cbf81d/resources/971_th1.jpg"}],"attributors":[{"name":"WIKWIO Project"}],"uploader":{"id":1,"name":"admin","icon":"http://portal.wikwio.org/biodiv/users/user_large.png"},"uploadTime":1426763415721,"language":{"id":137,"name":"French","threeLetterCode":"fre","twoLetterCode":"fr"},"rating":0},{"id":3145,"field":{"concept":"Généralités","category":"Synthèse","description":"Description générale du taxon mettant en évidence les principales caractériqtiques du taxon pour le grand public.","language":{"id":137,"name":"French","threeLetterCode":"fre","twoLetterCode":"fr"}},"text":"<h6>Code<\u002fh6><p>CEOTR<\u002fp><h6>Type Biologique<\u002fh6><p>feuilles larges<\u002fp><h6>Forme De Vie<\u002fh6><p>annuelle<\u002fp><h6>Habitat<\u002fh6><p>terrestre<\u002fp>","dateCreated":"2015-03-19T11:10:09Z","lastUpdated":"2015-03-19T11:10:09Z","licenses":[{"name":"CC BY-SA","url":"http://creativecommons.org/licenses/by-sa/3.0/ "}],"audienceTypes":[],"resources":[],"references":[],"contributors":[{"id":3,"name":"WIKWIO Portal","icon":"http://portal.wikwio.org/biodiv/users//23ff2afb-1bb8-45e2-a351-263413cbf81d/resources/971_th1.jpg"}],"attributors":[{"name":"WIKWIO Project"}],"uploader":{"id":1,"name":"admin","icon":"http://portal.wikwio.org/biodiv/users/user_large.png"},"uploadTime":1426763409490,"language":{"id":137,"name":"French","threeLetterCode":"fre","twoLetterCode":"fr"},"rating":0},{"id":3156,"field":{"concept":"Généralités","category":"Diagnostic","subCategory":"Description","description":"Un descriptif textuel de l'espèce pas nécessairement structuré.","language":{"id":137,"name":"French","threeLetterCode":"fre","twoLetterCode":"fr"}},"text":"<h6>\n\tDescription Globale<\u002fh6>\n<p>\n\t<em>Celosia trigyna<\u002fem> est une plante herbac&eacute;e dress&eacute;e pouvant atteindre 1 m de hauteur, &agrave; tige anguleuse peu ramifi&eacute;e. Les feuilles sont simples, alternes, longuement p&eacute;tiol&eacute;es &agrave; limbe ovale triangulaire. A la base des p&eacute;tioles se trouvent de 2 pi&egrave;ces foliac&eacute;es falciformes caract&eacute;ristiques de cette esp&egrave;ce. Les fleurs sont tr&egrave;s petites et assembl&eacute;es en boules blanches discontinues &agrave; l&#39;extr&eacute;mit&eacute; des rameaux. Les fruits sont de petites capsules globuleuses<\u002fp>\n<h6>\n\tCotyl&eacute;dons<\u002fh6>\n<p>\n\tLes cotyl&eacute;dons sont lanc&eacute;ol&eacute;s &agrave; elliptiques. Ils sont bri&egrave;vement p&eacute;tiol&eacute;s et mesurent 10 mm de long et 3 mm de large<\u002fp>\n<h6>\n\tPremi&egrave;res Feuilles<\u002fh6>\n<p>\n\tLes premi&egrave;res feuilles sont simples et alternes. Elles sont ovales et port&eacute;es par un p&eacute;tiole presque aussi long que le limbe.<\u002fp>\n<h6>\n\tPort<\u002fh6>\n<p>\n\tPlante dress&eacute;e, plus ou moins ramifi&eacute;e. Elle est haute de 40 &agrave; 100 cm<\u002fp>\n<h6>\n\tSyst&egrave;me Souterrain<\u002fh6>\n<p>\n\tLa racine est pivotante.<\u002fp>\n<h6>\n\tTige<\u002fh6>\n<p>\n\tLa tige est pleine et tr&egrave;s anguleuse ayant g&eacute;n&eacute;ralement 5 angles tr&egrave;s marqu&eacute;s. Elle est glabre.<\u002fp>\n<h6>\n\tFeuille<\u002fh6>\n<p>\n\tLes feuilles sont simples et alternes. Elles sont port&eacute;es par un long p&eacute;tiole de 3 &agrave; 8 cm, presque aussi long que le limbe. Le limbe est ovale &agrave; presque triangulaire, de 5 &agrave; 8 cm de long et 3 &agrave; 6 cm de large. La base est en coin parfois presque perpendiculaire au p&eacute;tiole. Le sommet est en coin. Les deux faces sont glabres. La marge est enti&egrave;re, finement scabre. Elles sont marqu&eacute;es par 6 &agrave; 10 nervures lat&eacute;rales. Un caract&egrave;re tr&egrave;s remarquable de cette esp&egrave;ce est la pr&eacute;sence, &agrave; la base des feuilles, de 2 pi&egrave;ces foliac&eacute;es falciformes de 10 &agrave; 15 mm de long, entourant la tige. Ces pi&egrave;ces foliac&eacute;es, ressemblant &agrave; des stipules, correspondent aux premi&egrave;res feuilles de rameaux axillaires plus ou moins d&eacute;velopp&eacute;s. Ce caract&egrave;re appara&icirc;t &agrave; partir de la quatri&egrave;me ou de la cinqui&egrave;me feuille.<\u002fp>\n<h6>\n\tInflorescence<\u002fh6>\n<p>\n\tL&#39;inflorescence est compos&eacute;e de glom&eacute;rules de tr&egrave;s petites fleurs blanches. Ces glom&eacute;rules sont eux-m&ecirc;mes dispos&eacute;s en &eacute;pis terminaux discontinus et plus ou moins ramifi&eacute;s.<\u002fp>\n<h6>\n\tFleur<\u002fh6>\n<p>\n\tLes fleurs sont constitu&eacute;es de 5 pi&egrave;ces membraneuses elliptiques de couleur blanche et mesurant 1,5 &agrave; 2 mm de long. A l&#39;int&eacute;rieur de ces pi&egrave;ces se trouvent 5 &eacute;tamines roses et un ovaire globuleux surmont&eacute; d&#39;un tr&egrave;s court style &agrave; trois branches<\u002fp>\n<h6>\n\tFruit<\u002fh6>\n<p>\n\tLe fruit est une capsule d&eacute;hiscente, globuleuse. Il mesure 1,5 &agrave; 2 mm de haut et 1,2 &agrave; 1,5 mm de large. L&#39;ouverture se fait par d&eacute;tachement de la moiti&eacute; sup&eacute;rieure de la capsule. Celle-ci est surmont&eacute;e par le tr&egrave;s court style trifide de 0,3 mm de haut. Une capsule contient 4 &agrave; 8 graines.<\u002fp>\n<h6>\n\tGraine<\u002fh6>\n<p>\n\tLa graine est r&eacute;niforme. Elle mesure 0,8 mm de diam&egrave;tre et 0,2 mm d&#39;&eacute;paisseur. Le t&eacute;gument est noir brillant<\u002fp>\n","dateCreated":"2015-03-19T11:10:11Z","lastUpdated":"2015-05-21T07:44:18Z","licenses":[{"name":"CC BY-SA","url":"http://creativecommons.org/licenses/by-sa/3.0/ "}],"audienceTypes":[],"resources":[],"references":[],"contributors":[{"id":3,"name":"WIKWIO Portal","icon":"http://portal.wikwio.org/biodiv/users//23ff2afb-1bb8-45e2-a351-263413cbf81d/resources/971_th1.jpg"}],"attributors":[{"name":"WIKWIO Project"}],"uploader":{"id":1,"name":"admin","icon":"http://portal.wikwio.org/biodiv/users/user_large.png"},"uploadTime":1426763411512,"language":{"id":137,"name":"French","threeLetterCode":"fre","twoLetterCode":"fr"},"rating":0},{"id":3158,"field":{"concept":"Nomenclature et Classification","category":"Nom de Taxon Enregistré","subCategory":"Nom Scientifique","description":"Le nom complet du taxon au niveau le plus bas auquel l'organisme a été identifié dans la détermination acceptée la plus récente, définis aussi précisément que possible, y compris le nom de l'auteur, l'année, sensu ou sec. (selon ou après) l'auteur, et l'indication de l'incertitude. Conceptuellement équivalent à une identification taxonomique complète.","language":{"id":137,"name":"French","threeLetterCode":"fre","twoLetterCode":"fr"}},"text":"Celosia trigyna L.","dateCreated":"2015-03-19T11:10:12Z","lastUpdated":"2015-03-19T11:10:12Z","licenses":[{"name":"CC BY-SA","url":"http://creativecommons.org/licenses/by-sa/3.0/ "}],"audienceTypes":[],"resources":[],"references":[],"contributors":[{"id":3,"name":"WIKWIO Portal","icon":"http://portal.wikwio.org/biodiv/users//23ff2afb-1bb8-45e2-a351-263413cbf81d/resources/971_th1.jpg"}],"attributors":[{"name":"WIKWIO Project"}],"uploader":{"id":1,"name":"admin","icon":"http://portal.wikwio.org/biodiv/users/user_large.png"},"uploadTime":1426763412024,"language":{"id":137,"name":"French","threeLetterCode":"fre","twoLetterCode":"fr"},"rating":0},{"id":3157,"field":{"concept":"Histoire Naturelle","category":"Cycle biologique","description":"Décrire le rythme biologique - Les états et conditions caractérisés par une répétition régulière dans le temps (seconde, heure, jour, saison). Cela peut inclure les phénomènes de floraison ou de rumination. Le cycle de vie est traité dans le champ \"Cycle de vie\". Migration saisonnière et reproduction sont traités séparément.","language":{"id":137,"name":"French","threeLetterCode":"fre","twoLetterCode":"fr"}},"text":"<strong>Nord-Cameroun <\u002fstrong>: <em>C. trigyna<\u002fem> est peu fr&eacute;quente en d&eacute;but de saison des pluies. La germination a lieu en juin lorsque les pluies deviennent abondantes et r&eacute;guli&egrave;res. Cette germination dure 1 &agrave; 2 semaines, mais peut &ecirc;tre retard&eacute;e par les travaux du sol de d&eacute;but de culture (labour, sarclage). La floraison d&eacute;bute en ao&ucirc;t et la fructification 3 semaines plus tard. La fructification se poursuit jusqu&#39;au dess&egrave;chement de la plante en d&eacute;but de saison s&egrave;che (novembre). Un cycle de d&eacute;veloppement complet dure 3 mois lorsque la germination a lieu en juin et seulement 3 &agrave; 4 semaines lorsque la germination a lieu en fin de cycle de la culture. La mise &agrave; fleur est li&eacute;e au raccourcissement de la longueur du jour.<br />\n<strong>Madagascar <\u002fstrong>:<em> C. trigyna<\u002fem> est une esp&egrave;ce de milieu et de fin de cycle des cultures pluviales. ","dateCreated":"2015-03-19T11:10:11Z","lastUpdated":"2015-05-21T07:44:36Z","licenses":[{"name":"CC BY-SA","url":"http://creativecommons.org/licenses/by-sa/3.0/ "}],"audienceTypes":[],"resources":[],"references":[],"contributors":[{"id":3,"name":"WIKWIO Portal","icon":"http://portal.wikwio.org/biodiv/users//23ff2afb-1bb8-45e2-a351-263413cbf81d/resources/971_th1.jpg"}],"attributors":[{"name":"WIKWIO Project"}],"uploader":{"id":1,"name":"admin","icon":"http://portal.wikwio.org/biodiv/users/user_large.png"},"uploadTime":1426763411780,"language":{"id":137,"name":"French","threeLetterCode":"fre","twoLetterCode":"fr"},"rating":0},{"id":3162,"field":{"concept":"Histoire Naturelle","category":"Reproduction","description":"Décrire le comportement et la physiologie de la reproduction, incluant fécondation et traits de vie (taux de reproduction...).","language":{"id":137,"name":"French","threeLetterCode":"fre","twoLetterCode":"fr"}},"text":"<em>C. trigyna<\u002fem> est une esp&egrave;ce annuelle. Elle se multiplie uniquement par graines. Celles-ci sont diss&eacute;min&eacute;es par le vent et l&#39;eau et les instruments de travail du sol.<br />\n","dateCreated":"2015-03-19T11:10:13Z","lastUpdated":"2015-05-21T07:44:45Z","licenses":[{"name":"CC BY-SA","url":"http://creativecommons.org/licenses/by-sa/3.0/ "}],"audienceTypes":[],"resources":[],"references":[],"contributors":[{"id":3,"name":"WIKWIO Portal","icon":"http://portal.wikwio.org/biodiv/users//23ff2afb-1bb8-45e2-a351-263413cbf81d/resources/971_th1.jpg"}],"attributors":[{"name":"WIKWIO Project"}],"uploader":{"id":1,"name":"admin","icon":"http://portal.wikwio.org/biodiv/users/user_large.png"},"uploadTime":1426763413051,"language":{"id":137,"name":"French","threeLetterCode":"fre","twoLetterCode":"fr"},"rating":0},{"id":6803,"field":{"concept":"Histoire Naturelle","category":"Ressemblance","description":"Autre taxon avec lequel il peut y avoir une confusion et mise en évidence des caractères de différenciation utiles pour l'identification et la comparaison.","language":{"id":137,"name":"French","threeLetterCode":"fre","twoLetterCode":"fr"}},"text":"<br />\n<table border=\"1\" cellpadding=\"1\" cellspacing=\"1\" height=\"204\" width=\"610\">\n\t<caption>\n\t\t<strong>Comparaison Celosia<\u002fstrong><\u002fcaption>\n\t<thead>\n\t\t<tr>\n\t\t\t<th scope=\"col\">\n\t\t\t<\u002fth>\n\t\t\t<th scope=\"col\" style=\"text-align: center; background-color: rgb(102, 255, 255);\">\n\t\t\t\tC. trigyna<\u002fth>\n\t\t\t<th scope=\"col\" style=\"text-align: center; background-color: rgb(102, 255, 255);\">\n\t\t\t\tC. argentea<\u002fth>\n\t\t<\u002ftr>\n\t<\u002fthead>\n\t<tbody>\n\t\t<tr>\n\t\t\t<td style=\"background-color: rgb(255, 255, 102);\">\n\t\t\t\t<strong>p&eacute;tiole<\u002fstrong><\u002ftd>\n\t\t\t<td style=\"text-align: center;\">\n\t\t\t\tlong<\u002ftd>\n\t\t\t<td style=\"text-align: center;\">\n\t\t\t\tcourt<\u002ftd>\n\t\t<\u002ftr>\n\t\t<tr>\n\t\t\t<td style=\"background-color: rgb(255, 255, 102);\">\n\t\t\t\t<strong>forme du limbe<\u002fstrong><\u002ftd>\n\t\t\t<td style=\"text-align: center;\">\n\t\t\t\tovale &agrave; presque triangulaire<\u002ftd>\n\t\t\t<td style=\"text-align: center;\">\n\t\t\t\tlanc&eacute;ol&eacute; &agrave; lin&eacute;aire<\u002ftd>\n\t\t<\u002ftr>\n\t\t<tr>\n\t\t\t<td style=\"background-color: rgb(255, 255, 102);\">\n\t\t\t\t<strong>base du limbe<\u002fstrong><\u002ftd>\n\t\t\t<td style=\"text-align: center;\">\n\t\t\t\tparfois presque perpendiculaire au p&eacute;tiole<\u002ftd>\n\t\t\t<td style=\"text-align: center;\">\n\t\t\t\tatt&eacute;nu&eacute;e<\u002ftd>\n\t\t<\u002ftr>\n\t\t<tr>\n\t\t\t<td style=\"background-color: rgb(255, 255, 102);\">\n\t\t\t\t<strong>inflorescence (forme)<\u002fstrong><\u002ftd>\n\t\t\t<td style=\"text-align: center;\">\n\t\t\t\tglom&eacute;rules de tr&egrave;s petites fleurs<\u002ftd>\n\t\t\t<td style=\"text-align: center;\">\n\t\t\t\t&eacute;pis denses terminaux<\u002ftd>\n\t\t<\u002ftr>\n\t\t<tr>\n\t\t\t<td style=\"background-color: rgb(255, 255, 102);\">\n\t\t\t\t<strong>inflorescence (couleur)<\u002fstrong><\u002ftd>\n\t\t\t<td style=\"text-align: center;\">\n\t\t\t\tblanche<\u002ftd>\n\t\t\t<td style=\"text-align: center;\">\n\t\t\t\tblanc ros&eacute; &agrave; rose vif<\u002ftd>\n\t\t<\u002ftr>\n\t<\u002ftbody>\n<\u002ftable>\n<p>\n<\u002fp>\n","dateCreated":"2015-07-03T09:23:54Z","lastUpdated":"2015-07-03T09:26:43Z","licenses":[{"name":"CC BY","url":"http://creativecommons.org/licenses/by/3.0/"}],"audienceTypes":[{"enumType":"species.SpeciesField$AudienceType","name":"GENERAL_PUBLIC"}],"resources":[],"references":[],"contributors":[{"id":36,"name":"Marnotte Pascal","icon":"http://portal.wikwio.org/biodiv/users//097b0e2c-495a-4219-bf9f-5a2f78a0889c/resources/330_th1.jpg"}],"attributors":[],"uploader":{"id":36,"name":"Marnotte Pascal","icon":"http://portal.wikwio.org/biodiv/users//097b0e2c-495a-4219-bf9f-5a2f78a0889c/resources/330_th1.jpg"},"uploadTime":1435915434021,"language":{"id":137,"name":"French","threeLetterCode":"fre","twoLetterCode":"fr"},"rating":0},{"id":3161,"field":{"concept":"Histoire Naturelle","category":"Ecologie","description":"Relations interorganismes dans leur environnement. Variables d'intérêt pour l'écologie (composition, distribution, biomasse, allelopathie).","language":{"id":137,"name":"French","threeLetterCode":"fre","twoLetterCode":"fr"}},"text":"<strong>Nord-Cameroun :<\u002fstrong> <em>C. trigyna<\u002fem> est une adventice tr&egrave;s commune des cultures annuelles dans les r&eacute;gions &agrave; climat soudano-sah&eacute;lien &agrave; soudanien dont la pluviom&eacute;trie annuelle est sup&eacute;rieure &agrave; 800 mm. Elle est alors pr&eacute;sente dans 30 % des parcelles. Elle n&#39;a pas de pr&eacute;f&eacute;rence de sol notable et cro&icirc;t aussi bien sur sol ferrugineux d&eacute;grad&eacute; que sur planosol. En r&eacute;gion sah&eacute;lo-soudanienne, elle est tr&egrave;s rare et ne se d&eacute;veloppe que sur les sols &agrave; forte r&eacute;tention d&#39;eau. C&#39;est une adventice caract&eacute;ristique des parcelles cultiv&eacute;es depuis de nombreuses ann&eacute;es et faisant l&#39;objet d&#39;itin&eacute;raires techniques semi-intensifs (culture attel&eacute;e, fumure min&eacute;rale) ou intensifs (culture attel&eacute;e, forte fumure min&eacute;rale et utilisation r&eacute;p&eacute;t&eacute;e d&#39;herbicides de pr&eacute;-lev&eacute;e du cotonnier). Elle appartient au cort&egrave;ge floristique de <em>Commelina benghalensis<\u002fem>. Bien que fr&eacute;quente en zone soudanienne, elle est rarement abondante.<br />\n<strong>Madagascar : <\u002fstrong>L&#39;esp&egrave;ce se d&eacute;veloppe sur les sols ferralitiques, sols ferrugineux et alluvions assez fertiles en terrain ensoleill&eacute;. C&#39;est une adventice des cultures pluviales (ma&iuml;s, cotonnier, arachide) en zones semi-aride et subhumides jusqu&rsquo;&agrave; 1200 m d&#39;altitude dans les syst&egrave;mes de culture semi-intensifs sans fertilisation. Les zones agro-&eacute;cologiques concern&eacute;es &agrave; Madagascar sont le Sud-ouest, Ouest, Nord-ouest et Hautes terres.<br />\n<strong>Maurice :<\u002fstrong> absente.<br />\n<strong>La R&eacute;union <\u002fstrong>: absente.<br />\n<strong>Seychelles<\u002fstrong> : absente<br />\n","dateCreated":"2015-03-19T11:10:12Z","lastUpdated":"2015-05-21T07:45:06Z","licenses":[{"name":"CC BY-SA","url":"http://creativecommons.org/licenses/by-sa/3.0/ "}],"audienceTypes":[],"resources":[],"references":[],"contributors":[{"id":3,"name":"WIKWIO Portal","icon":"http://portal.wikwio.org/biodiv/users//23ff2afb-1bb8-45e2-a351-263413cbf81d/resources/971_th1.jpg"}],"attributors":[{"name":"WIKWIO Project"}],"uploader":{"id":1,"name":"admin","icon":"http://portal.wikwio.org/biodiv/users/user_large.png"},"uploadTime":1426763412807,"language":{"id":137,"name":"French","threeLetterCode":"fre","twoLetterCode":"fr"},"rating":0},{"id":3160,"field":{"concept":"Habitat et Distribution","category":"Distribution","subCategory":"Description","description":"Énumérer les entités géographiques où le taxon vit. Couvre par exemple, une région globale, ou une plus étroite; peut être biogéographique, politique ou autre (par exemple, les zones gérées pour la conservation) ; endémisme; indigène ou exotique. Ne comprend pas la distribution altitudinale, qui est traité dans le champ \"habitat\".","language":{"id":137,"name":"French","threeLetterCode":"fre","twoLetterCode":"fr"}},"text":"<h6>Distribution Mondiale<\u002fh6><p>Cette espèce est très répandue en Afrique, également dans la péninsule arabique et à Madagascar.<\u002fp>","dateCreated":"2015-03-19T11:10:12Z","lastUpdated":"2015-03-19T11:10:12Z","licenses":[{"name":"CC BY-SA","url":"http://creativecommons.org/licenses/by-sa/3.0/ "}],"audienceTypes":[],"resources":[],"references":[],"contributors":[{"id":3,"name":"WIKWIO Portal","icon":"http://portal.wikwio.org/biodiv/users//23ff2afb-1bb8-45e2-a351-263413cbf81d/resources/971_th1.jpg"}],"attributors":[{"name":"WIKWIO Project"}],"uploader":{"id":1,"name":"admin","icon":"http://portal.wikwio.org/biodiv/users/user_large.png"},"uploadTime":1426763412538,"language":{"id":137,"name":"French","threeLetterCode":"fre","twoLetterCode":"fr"},"rating":0},{"id":3163,"field":{"concept":"Démographie et Conservation","category":"Analyse de Risque","description":"Impacts négatifs sur les communautés humaines incluant l'invasibilité. [Cela peut concerner les écosystèmes où l'organisme est en déclin ou a été éliminé]","language":{"id":137,"name":"French","threeLetterCode":"fre","twoLetterCode":"fr"}},"text":"<h6>\n\tNuisibilit&eacute; locale<\u002fh6>\n<p>\n\t<strong>Madagascar <\u002fstrong>: <em>C. trigyna<\u002fem> est une adventice de fr&eacute;quence moyenne et d&rsquo;abondance g&eacute;n&eacute;ralement faible &agrave; moyenne dans les cultures pluviales : riz pluvial, cotonnier, ma&iuml;s. En fin de cycle, elle peut &ecirc;tre toutefois tr&egrave;s g&ecirc;nante pour les travaux de r&eacute;colte en raison de son d&eacute;veloppement v&eacute;g&eacute;tatif.<br />\n\t<strong>Maurice :<\u002fstrong> absente.<br />\n\t<strong>La R&eacute;union<\u002fstrong> : absente.<br />\n\t<strong>Seychelles <\u002fstrong>: absente.<\u002fp>\n","dateCreated":"2015-03-19T11:10:13Z","lastUpdated":"2015-12-09T08:23:36Z","licenses":[{"name":"CC BY-SA","url":"http://creativecommons.org/licenses/by-sa/3.0/ "}],"audienceTypes":[],"resources":[],"references":[],"contributors":[{"id":3,"name":"WIKWIO Portal","icon":"http://portal.wikwio.org/biodiv/users//23ff2afb-1bb8-45e2-a351-263413cbf81d/resources/971_th1.jpg"}],"attributors":[{"name":"WIKWIO Project"}],"uploader":{"id":1,"name":"admin","icon":"http://portal.wikwio.org/biodiv/users/user_large.png"},"uploadTime":1426763413322,"language":{"id":137,"name":"French","threeLetterCode":"fre","twoLetterCode":"fr"},"rating":0},{"id":6635,"field":{"concept":"Usages et Gestion","category":"Usages","description":"Décrire les usages connus ou avantages potentiels de l'espèce pour l'homme, au niveau économique direct, comme des instruments de l'éducation, de la prospection, de l'éco-tourisme, etc. La source doit être explicitement citée. Peut inclure des services écosystémiques.","language":{"id":137,"name":"French","threeLetterCode":"fre","twoLetterCode":"fr"}},"text":"<strong>Alimentaire :<\u002fstrong> Les feuilles de <em>C. trigyna <\u002fem>avec les jeunes tiges sont consomm&eacute;es comme l&eacute;gumes.<br />\n<br />\n<strong>Alimentation du b&eacute;tail : <\u002fstrong>La plante enti&egrave;re peut &ecirc;tre utilis&eacute;e comme fourrage en particulier pour les lapins.<br />\n<br />\n<strong>M&eacute;dicinal : <\u002fstrong><em>C. trigyna<\u002fem> est utilis&eacute; en m&eacute;decine traditionnelle contre les douleurs cardiaques. Les activit&eacute;s anti inflammatoires et anti oxydants des extraits de la plante sont prouv&eacute;es.\n<p>\n<\u002fp>\n","dateCreated":"2015-04-22T11:42:10Z","lastUpdated":"2015-12-09T08:23:20Z","licenses":[{"name":"CC BY","url":"http://creativecommons.org/licenses/by/3.0/"}],"audienceTypes":[{"enumType":"species.SpeciesField$AudienceType","name":"GENERAL_PUBLIC"}],"resources":[],"references":[],"contributors":[{"id":4,"name":"Thomas Le Bourgeois","icon":"http://portal.wikwio.org/biodiv/users//13b7c53d-06c9-4129-9509-346ddce6e458/resources/390_th1.jpg"}],"attributors":[],"uploader":{"id":4,"name":"Thomas Le Bourgeois","icon":"http://portal.wikwio.org/biodiv/users//13b7c53d-06c9-4129-9509-346ddce6e458/resources/390_th1.jpg"},"uploadTime":1429702930653,"language":{"id":137,"name":"French","threeLetterCode":"fre","twoLetterCode":"fr"},"rating":0},{"id":6636,"field":{"concept":"Usages et Gestion","category":"Gestion","description":"Décrire les techniques et les objectifs utilisés dans la gestion des espèces - élevage et de culture, lutte, etc. Peut inclure la gestion par rapport à un projet de loi, par exemple, une liste de la CITES.","language":{"id":137,"name":"French","threeLetterCode":"fre","twoLetterCode":"fr"}},"text":"<strong>Lutte locale<\u002fstrong><br />\n<br />\n<strong>Madagascar : <\u002fstrong>A Madagascar, le sarclage manuel reste pratiquement le seul moyen de lutte pratiqu&eacute; contre <em>C. trigyna<\u002fem>.\n<p>\n<\u002fp>\n","dateCreated":"2015-04-22T11:42:17Z","lastUpdated":"2015-09-08T19:30:03Z","licenses":[{"name":"CC BY","url":"http://creativecommons.org/licenses/by/3.0/"}],"audienceTypes":[{"enumType":"species.SpeciesField$AudienceType","name":"GENERAL_PUBLIC"}],"resources":[],"references":[],"contributors":[{"id":4,"name":"Thomas Le Bourgeois","icon":"http://portal.wikwio.org/biodiv/users//13b7c53d-06c9-4129-9509-346ddce6e458/resources/390_th1.jpg"}],"attributors":[],"uploader":{"id":4,"name":"Thomas Le Bourgeois","icon":"http://portal.wikwio.org/biodiv/users//13b7c53d-06c9-4129-9509-346ddce6e458/resources/390_th1.jpg"},"uploadTime":1429702937134,"language":{"id":137,"name":"French","threeLetterCode":"fre","twoLetterCode":"fr"},"rating":0},{"id":3150,"field":{"concept":"Liste d'Information","category":"Références","description":"Bibliographie","language":{"id":137,"name":"French","threeLetterCode":"fre","twoLetterCode":"fr"}},"text":"dummy","dateCreated":"2015-03-19T11:10:11Z","lastUpdated":"2015-03-31T06:52:52Z","licenses":[{"name":"CC BY-SA","url":"http://creativecommons.org/licenses/by-sa/3.0/ "}],"audienceTypes":[],"resources":[],"references":[{"title":"Berhaut J., 1971. Flore illustrée du Sénégal. Tome 1. Clairafrique éd., Dakar, Sénégal, 626 p."}],"contributors":[{"id":3,"name":"WIKWIO Portal","icon":"http://portal.wikwio.org/biodiv/users//23ff2afb-1bb8-45e2-a351-263413cbf81d/resources/971_th1.jpg"}],"attributors":[{"name":"WIKWIO Project"}],"uploader":{"id":1,"name":"admin","icon":"http://portal.wikwio.org/biodiv/users/user_large.png"},"uploadTime":1426763411065,"language":{"id":137,"name":"French","threeLetterCode":"fre","twoLetterCode":"fr"},"rating":0},{"id":3149,"field":{"concept":"Liste d'Information","category":"Références","description":"Bibliographie","language":{"id":137,"name":"French","threeLetterCode":"fre","twoLetterCode":"fr"}},"text":"dummy","dateCreated":"2015-03-19T11:10:11Z","lastUpdated":"2015-03-31T06:52:52Z","licenses":[{"name":"CC BY-SA","url":"http://creativecommons.org/licenses/by-sa/3.0/ "}],"audienceTypes":[],"resources":[],"references":[{"title":"Berhaut J., 1967. Flore du Sénégal. 2ème éd. Clairafrique éd., Dakar, Sénégal, 485 p."}],"contributors":[{"id":3,"name":"WIKWIO Portal","icon":"http://portal.wikwio.org/biodiv/users//23ff2afb-1bb8-45e2-a351-263413cbf81d/resources/971_th1.jpg"}],"attributors":[{"name":"WIKWIO Project"}],"uploader":{"id":1,"name":"admin","icon":"http://portal.wikwio.org/biodiv/users/user_large.png"},"uploadTime":1426763411065,"language":{"id":137,"name":"French","threeLetterCode":"fre","twoLetterCode":"fr"},"rating":0},{"id":3148,"field":{"concept":"Liste d'Information","category":"Références","description":"Bibliographie","language":{"id":137,"name":"French","threeLetterCode":"fre","twoLetterCode":"fr"}},"text":"dummy","dateCreated":"2015-03-19T11:10:11Z","lastUpdated":"2015-03-31T06:52:52Z","licenses":[{"name":"CC BY-SA","url":"http://creativecommons.org/licenses/by-sa/3.0/ "}],"audienceTypes":[],"resources":[],"references":[{"title":"Akobundu I.O. & Agyakwa C.W., 1989. Guide des adventices d'Afrique de l'Ouest. Institut international d'agriculture tropicale. Ibadan, Nigeria, 521 p."}],"contributors":[{"id":3,"name":"WIKWIO Portal","icon":"http://portal.wikwio.org/biodiv/users//23ff2afb-1bb8-45e2-a351-263413cbf81d/resources/971_th1.jpg"}],"attributors":[{"name":"WIKWIO Project"}],"uploader":{"id":1,"name":"admin","icon":"http://portal.wikwio.org/biodiv/users/user_large.png"},"uploadTime":1426763411065,"language":{"id":137,"name":"French","threeLetterCode":"fre","twoLetterCode":"fr"},"rating":0},{"id":3147,"field":{"concept":"Liste d'Information","category":"Références","description":"Bibliographie","language":{"id":137,"name":"French","threeLetterCode":"fre","twoLetterCode":"fr"}},"text":"dummy","dateCreated":"2015-03-19T11:10:11Z","lastUpdated":"2015-03-30T16:35:16Z","licenses":[{"name":"CC BY-SA","url":"http://creativecommons.org/licenses/by-sa/3.0/ "}],"audienceTypes":[],"resources":[],"references":[],"contributors":[{"id":3,"name":"WIKWIO Portal","icon":"http://portal.wikwio.org/biodiv/users//23ff2afb-1bb8-45e2-a351-263413cbf81d/resources/971_th1.jpg"}],"attributors":[{"name":"WIKWIO Project"}],"uploader":{"id":1,"name":"admin","icon":"http://portal.wikwio.org/biodiv/users/user_large.png"},"uploadTime":1426763411064,"language":{"id":137,"name":"French","threeLetterCode":"fre","twoLetterCode":"fr"},"rating":0},{"id":3154,"field":{"concept":"Liste d'Information","category":"Références","description":"Bibliographie","language":{"id":137,"name":"French","threeLetterCode":"fre","twoLetterCode":"fr"}},"text":"dummy","dateCreated":"2015-03-19T11:10:11Z","lastUpdated":"2015-03-31T06:52:52Z","licenses":[{"name":"CC BY-SA","url":"http://creativecommons.org/licenses/by-sa/3.0/ "}],"audienceTypes":[],"resources":[],"references":[{"title":"Merlier H. & Montégut J., 1982. Adventices tropicales. ORSTOM-GERDAT-ENSH éd., Montpellier, France, 490 p."}],"contributors":[{"id":3,"name":"WIKWIO Portal","icon":"http://portal.wikwio.org/biodiv/users//23ff2afb-1bb8-45e2-a351-263413cbf81d/resources/971_th1.jpg"}],"attributors":[{"name":"WIKWIO Project"}],"uploader":{"id":1,"name":"admin","icon":"http://portal.wikwio.org/biodiv/users/user_large.png"},"uploadTime":1426763411066,"language":{"id":137,"name":"French","threeLetterCode":"fre","twoLetterCode":"fr"},"rating":0},{"id":6637,"field":{"concept":"Liste d'Information","category":"Références","description":"Bibliographie","language":{"id":137,"name":"French","threeLetterCode":"fre","twoLetterCode":"fr"}},"text":"dummy","dateCreated":"2015-04-22T11:43:09Z","lastUpdated":"2015-04-22T11:43:09Z","licenses":[{"name":"CC BY","url":"http://creativecommons.org/licenses/by/3.0/"}],"audienceTypes":[{"enumType":"species.SpeciesField$AudienceType","name":"GENERAL_PUBLIC"}],"resources":[],"references":[{"title":"LARBIE C. & MENSAH A. D. 2014. Botanicals for managing cardiovascular disorders : A review of medicinal weeds on Knust Campus. Global J Res. Med. Plants & Indigen. Med. Volume 3, Issue 9 September 2014, 349-358"},{"title":"CAVACO A. 1954 Flore de Madagascar, fasc.67 AMARANTHACEES, 56 pages"},{"url":"http://database.prota.org/PROTAhtml/Celosia%20trigyna_En.htm"},{"title":"MAROYI A. 2013. Use of weeds as traditional vegetables in Shurugwi District, Zimbabwe Journal of Ethnobiology and Ethnomedicine 2013, 9:60,p 1-10.Montpellier, France, 490 p."}],"contributors":[{"id":4,"name":"Thomas Le Bourgeois","icon":"http://portal.wikwio.org/biodiv/users//13b7c53d-06c9-4129-9509-346ddce6e458/resources/390_th1.jpg"}],"attributors":[],"uploader":{"id":4,"name":"Thomas Le Bourgeois","icon":"http://portal.wikwio.org/biodiv/users//13b7c53d-06c9-4129-9509-346ddce6e458/resources/390_th1.jpg"},"uploadTime":1429702989490,"language":{"id":137,"name":"French","threeLetterCode":"fre","twoLetterCode":"fr"},"rating":0},{"id":3155,"field":{"concept":"Liste d'Information","category":"Références","description":"Bibliographie","language":{"id":137,"name":"French","threeLetterCode":"fre","twoLetterCode":"fr"}},"text":"dummy","dateCreated":"2015-03-19T11:10:11Z","lastUpdated":"2015-03-31T06:52:52Z","licenses":[{"name":"CC BY-SA","url":"http://creativecommons.org/licenses/by-sa/3.0/ "}],"audienceTypes":[],"resources":[],"references":[{"title":"http://idao.cirad.fr/SpecieSheet?sheet=adventoi/especes/c/ceotr/ceotr_fr.html"}],"contributors":[{"id":3,"name":"WIKWIO Portal","icon":"http://portal.wikwio.org/biodiv/users//23ff2afb-1bb8-45e2-a351-263413cbf81d/resources/971_th1.jpg"}],"attributors":[{"name":"WIKWIO Project"}],"uploader":{"id":1,"name":"admin","icon":"http://portal.wikwio.org/biodiv/users/user_large.png"},"uploadTime":1426763411066,"language":{"id":137,"name":"French","threeLetterCode":"fre","twoLetterCode":"fr"},"rating":0},{"id":3146,"field":{"concept":"Liste d'Information","category":"Références","description":"Bibliographie","language":{"id":137,"name":"French","threeLetterCode":"fre","twoLetterCode":"fr"}},"text":"dummy","dateCreated":"2015-03-19T11:10:11Z","lastUpdated":"2015-04-01T09:47:00Z","licenses":[{"name":"CC BY-SA","url":"http://creativecommons.org/licenses/by-sa/3.0/ "}],"audienceTypes":[],"resources":[],"references":[{"title":"Le Bourgeois, T. and H. Merlier (1995). Adventrop - Les adventices d'Afrique soudano-sahélienne. Montpellier, France, Cirad. 640 p."},{"title":"Le Bourgeois, T., A. Carrara, M. Dodet, W. Dogley, A. Gaungoo, P. Grard, Y. Ibrahim, E. Jeuffrault, G. Lebreton, P. Poilecot, J. Prosperi, J. A. Randriamampianina, A. P. Andrianaivo and F. Théveny (2008). Advent-OI : Principales adventices des îles du sud-ouest de l'Océan Indien. Cirad. Montpellier, France, Cirad."}],"contributors":[{"id":3,"name":"WIKWIO Portal","icon":"http://portal.wikwio.org/biodiv/users//23ff2afb-1bb8-45e2-a351-263413cbf81d/resources/971_th1.jpg"}],"attributors":[{"name":"WIKWIO Project"}],"uploader":{"id":1,"name":"admin","icon":"http://portal.wikwio.org/biodiv/users/user_large.png"},"uploadTime":1426763411064,"language":{"id":137,"name":"French","threeLetterCode":"fre","twoLetterCode":"fr"},"rating":0},{"id":3153,"field":{"concept":"Liste d'Information","category":"Références","description":"Bibliographie","language":{"id":137,"name":"French","threeLetterCode":"fre","twoLetterCode":"fr"}},"text":"dummy","dateCreated":"2015-03-19T11:10:11Z","lastUpdated":"2015-03-31T06:52:52Z","licenses":[{"name":"CC BY-SA","url":"http://creativecommons.org/licenses/by-sa/3.0/ "}],"audienceTypes":[],"resources":[],"references":[{"title":"le Bourgeois Th., 1993. Les mauvaises herbes dans la rotation cotonnière au Nord-Cameroun (Afrique) - Amplitude d'habitat et degré d'infestation - Cycle de développement. Thèse USTL Montpellier II, Montpellier, France, 241 p."}],"contributors":[{"id":3,"name":"WIKWIO Portal","icon":"http://portal.wikwio.org/biodiv/users//23ff2afb-1bb8-45e2-a351-263413cbf81d/resources/971_th1.jpg"}],"attributors":[{"name":"WIKWIO Project"}],"uploader":{"id":1,"name":"admin","icon":"http://portal.wikwio.org/biodiv/users/user_large.png"},"uploadTime":1426763411066,"language":{"id":137,"name":"French","threeLetterCode":"fre","twoLetterCode":"fr"},"rating":0},{"id":3152,"field":{"concept":"Liste d'Information","category":"Références","description":"Bibliographie","language":{"id":137,"name":"French","threeLetterCode":"fre","twoLetterCode":"fr"}},"text":"dummy","dateCreated":"2015-03-19T11:10:11Z","lastUpdated":"2015-03-31T06:52:52Z","licenses":[{"name":"CC BY-SA","url":"http://creativecommons.org/licenses/by-sa/3.0/ "}],"audienceTypes":[],"resources":[],"references":[{"title":"Ivens G. W., Moody K. & Egunjobi J. K., 1978. West African Weeds. Oxford University Press, Ibadan, Nigeria, 255 p."}],"contributors":[{"id":3,"name":"WIKWIO Portal","icon":"http://portal.wikwio.org/biodiv/users//23ff2afb-1bb8-45e2-a351-263413cbf81d/resources/971_th1.jpg"}],"attributors":[{"name":"WIKWIO Project"}],"uploader":{"id":1,"name":"admin","icon":"http://portal.wikwio.org/biodiv/users/user_large.png"},"uploadTime":1426763411065,"language":{"id":137,"name":"French","threeLetterCode":"fre","twoLetterCode":"fr"},"rating":0},{"id":3151,"field":{"concept":"Liste d'Information","category":"Références","description":"Bibliographie","language":{"id":137,"name":"French","threeLetterCode":"fre","twoLetterCode":"fr"}},"text":"dummy","dateCreated":"2015-03-19T11:10:11Z","lastUpdated":"2015-03-31T06:52:52Z","licenses":[{"name":"CC BY-SA","url":"http://creativecommons.org/licenses/by-sa/3.0/ "}],"audienceTypes":[],"resources":[],"references":[{"title":"Hutchinson J., Dalziel J. M., Keay R. W. J. & Hepper F. N., 1954. Flora of West Tropical Africa. Vol. I part. 1. 2ème éd. The Whitefriars Press ed., London & Tonbridge, 295 p."}],"contributors":[{"id":3,"name":"WIKWIO Portal","icon":"http://portal.wikwio.org/biodiv/users//23ff2afb-1bb8-45e2-a351-263413cbf81d/resources/971_th1.jpg"}],"attributors":[{"name":"WIKWIO Project"}],"uploader":{"id":1,"name":"admin","icon":"http://portal.wikwio.org/biodiv/users/user_large.png"},"uploadTime":1426763411065,"language":{"id":137,"name":"French","threeLetterCode":"fre","twoLetterCode":"fr"},"rating":0}],"resource":[{"id":928,"description":"Celosia trigyna L.","uploader":{"id":4,"name":"Thomas Le Bourgeois","icon":"http://portal.wikwio.org/biodiv/users//13b7c53d-06c9-4129-9509-346ddce6e458/resources/390_th1.jpg"},"type":"Image","uploadTime":"2015-06-23T12:55:31Z","rating":0,"totalRatings":1,"averageRating":3.0,"license":{"name":"CC BY-SA","url":"http://creativecommons.org/licenses/by-sa/3.0/ "},"contributors":[{"name":"Thomas LE BOURGEOIS / CIRAD"}],"attributors":[],"annotations":{},"url":"http://portal.wikwio.org/biodiv/img//Celosia trigyna/ceotr_20080609_101206_04.jpg","icon":"http://portal.wikwio.org/biodiv/img//Celosia trigyna/ceotr_20080609_101206_04_th1.jpg"},{"id":17708,"description":null,"uploader":{"id":4,"name":"Thomas Le Bourgeois","icon":"http://portal.wikwio.org/biodiv/users//13b7c53d-06c9-4129-9509-346ddce6e458/resources/390_th1.jpg"},"type":"Image","uploadTime":"2015-06-23T12:55:31Z","rating":0,"totalRatings":1,"averageRating":3.0,"license":{"name":"CC BY-SA","url":"http://creativecommons.org/licenses/by-sa/3.0/ "},"contributors":[{"name":"Marcel Maminirina / FOFIFA"}],"attributors":[],"annotations":{},"url":"http://portal.wikwio.org/biodiv/img//Celosia trigyna/464.jpg","icon":"http://portal.wikwio.org/biodiv/img//Celosia trigyna/464_th1.jpg"},{"id":17710,"description":null,"uploader":{"id":4,"name":"Thomas Le Bourgeois","icon":"http://portal.wikwio.org/biodiv/users//13b7c53d-06c9-4129-9509-346ddce6e458/resources/390_th1.jpg"},"type":"Image","uploadTime":"2015-06-23T12:55:31Z","rating":0,"totalRatings":2,"averageRating":2.5,"license":{"name":"CC BY-SA","url":"http://creativecommons.org/licenses/by-sa/3.0/ "},"contributors":[{"name":"Marcel Maminirina / FOFIFA"}],"attributors":[],"annotations":{},"url":"http://portal.wikwio.org/biodiv/img//Celosia trigyna/884.jpg","icon":"http://portal.wikwio.org/biodiv/img//Celosia trigyna/884_th1.jpg"},{"id":17709,"description":null,"uploader":{"id":4,"name":"Thomas Le Bourgeois","icon":"http://portal.wikwio.org/biodiv/users//13b7c53d-06c9-4129-9509-346ddce6e458/resources/390_th1.jpg"},"type":"Image","uploadTime":"2015-06-23T12:55:31Z","rating":0,"totalRatings":2,"averageRating":2.0,"license":{"name":"CC BY-SA","url":"http://creativecommons.org/licenses/by-sa/3.0/ "},"contributors":[{"name":"Marcel Maminirina / FOFIFA"}],"attributors":[],"annotations":{},"url":"http://portal.wikwio.org/biodiv/img//Celosia trigyna/306.jpg","icon":"http://portal.wikwio.org/biodiv/img//Celosia trigyna/306_th1.jpg"},{"id":20130,"description":"","uploader":{"id":36,"name":"Marnotte Pascal","icon":"http://portal.wikwio.org/biodiv/users//097b0e2c-495a-4219-bf9f-5a2f78a0889c/resources/330_th1.jpg"},"type":"Image","uploadTime":"2016-02-08T09:18:53Z","rating":0,"totalRatings":1,"averageRating":2.0,"license":{"name":"CC BY","url":"http://creativecommons.org/licenses/by/3.0/"},"contributors":[{"name":"pascal.marnotte"}],"attributors":[],"annotations":{},"url":"http://portal.wikwio.org/biodiv/observations//95befecc-dd63-4633-98ba-bb71821475b8/296.JPG","icon":"http://portal.wikwio.org/biodiv/observations//95befecc-dd63-4633-98ba-bb71821475b8/296_th1.jpg"},{"id":922,"description":"Celosia trigyna L.","uploader":{"id":4,"name":"Thomas Le Bourgeois","icon":"http://portal.wikwio.org/biodiv/users//13b7c53d-06c9-4129-9509-346ddce6e458/resources/390_th1.jpg"},"type":"Image","uploadTime":"2015-06-23T12:55:31Z","rating":0,"totalRatings":0,"averageRating":0,"license":{"name":"CC BY-SA","url":"http://creativecommons.org/licenses/by-sa/3.0/ "},"contributors":[{"name":"Thomas LE BOURGEOIS / CIRAD"}],"attributors":[],"annotations":{},"url":"http://portal.wikwio.org/biodiv/img//Celosia trigyna/ceotr_20080609_101206_07.jpg","icon":"http://portal.wikwio.org/biodiv/img//Celosia trigyna/ceotr_20080609_101206_07_th1.jpg"},{"id":923,"description":"Celosia trigyna L.","uploader":{"id":4,"name":"Thomas Le Bourgeois","icon":"http://portal.wikwio.org/biodiv/users//13b7c53d-06c9-4129-9509-346ddce6e458/resources/390_th1.jpg"},"type":"Image","uploadTime":"2015-06-23T12:55:31Z","rating":0,"totalRatings":0,"averageRating":0,"license":{"name":"CC BY-SA","url":"http://creativecommons.org/licenses/by-sa/3.0/ "},"contributors":[{"name":"Thomas LE BOURGEOIS / CIRAD"}],"attributors":[],"annotations":{},"url":"http://portal.wikwio.org/biodiv/img//Celosia trigyna/ceotr_20090217_171225.jpg","icon":"http://portal.wikwio.org/biodiv/img//Celosia trigyna/ceotr_20090217_171225_th1.jpg"},{"id":925,"description":"Celosia trigyna L.","uploader":{"id":4,"name":"Thomas Le Bourgeois","icon":"http://portal.wikwio.org/biodiv/users//13b7c53d-06c9-4129-9509-346ddce6e458/resources/390_th1.jpg"},"type":"Image","uploadTime":"2015-06-23T12:55:31Z","rating":0,"totalRatings":0,"averageRating":0,"license":{"name":"CC BY-SA","url":"http://creativecommons.org/licenses/by-sa/3.0/ "},"contributors":[{"name":"Thomas LE BOURGEOIS / CIRAD"}],"attributors":[],"annotations":{},"url":"http://portal.wikwio.org/biodiv/img//Celosia trigyna/ceotr_20090216_191552.jpg","icon":"http://portal.wikwio.org/biodiv/img//Celosia trigyna/ceotr_20090216_191552_th1.jpg"},{"id":926,"description":"Celosia trigyna L.","uploader":{"id":4,"name":"Thomas Le Bourgeois","icon":"http://portal.wikwio.org/biodiv/users//13b7c53d-06c9-4129-9509-346ddce6e458/resources/390_th1.jpg"},"type":"Image","uploadTime":"2015-06-23T12:55:30Z","rating":0,"totalRatings":0,"averageRating":0,"license":{"name":"CC BY-SA","url":"http://creativecommons.org/licenses/by-sa/3.0/ "},"contributors":[{"name":"Jean Augustin RANDRIAMANPIANINA / FOFIFA"}],"attributors":[],"annotations":{},"url":"http://portal.wikwio.org/biodiv/img//Celosia trigyna/ceotr_20080609_101206_08.jpg","icon":"http://portal.wikwio.org/biodiv/img//Celosia trigyna/ceotr_20080609_101206_08_th1.jpg"},{"id":927,"description":"Celosia trigyna L.","uploader":{"id":4,"name":"Thomas Le Bourgeois","icon":"http://portal.wikwio.org/biodiv/users//13b7c53d-06c9-4129-9509-346ddce6e458/resources/390_th1.jpg"},"type":"Image","uploadTime":"2015-06-23T12:55:30Z","rating":0,"totalRatings":0,"averageRating":0,"license":{"name":"CC BY-SA","url":"http://creativecommons.org/licenses/by-sa/3.0/ "},"contributors":[{"name":"Thomas LE BOURGEOIS / CIRAD"}],"attributors":[],"annotations":{},"url":"http://portal.wikwio.org/biodiv/img//Celosia trigyna/ceotr_20090216_191636.jpg","icon":"http://portal.wikwio.org/biodiv/img//Celosia trigyna/ceotr_20090216_191636_th1.jpg"},{"id":932,"description":"Celosia trigyna L.","uploader":{"id":4,"name":"Thomas Le Bourgeois","icon":"http://portal.wikwio.org/biodiv/users//13b7c53d-06c9-4129-9509-346ddce6e458/resources/390_th1.jpg"},"type":"Image","uploadTime":"2015-06-23T12:55:31Z","rating":0,"totalRatings":0,"averageRating":0,"license":{"name":"CC BY-SA","url":"http://creativecommons.org/licenses/by-sa/3.0/ "},"contributors":[{"name":"Jean ASSI YAPO / Herbarium national de l'Université d'Abidjan"}],"attributors":[],"annotations":{},"url":"http://portal.wikwio.org/biodiv/img//Celosia trigyna/ceotr_20121120_102820.jpg","icon":"http://portal.wikwio.org/biodiv/img//Celosia trigyna/ceotr_20121120_102820_th1.jpg"},{"id":933,"description":"Celosia trigyna L.","uploader":{"id":4,"name":"Thomas Le Bourgeois","icon":"http://portal.wikwio.org/biodiv/users//13b7c53d-06c9-4129-9509-346ddce6e458/resources/390_th1.jpg"},"type":"Image","uploadTime":"2015-06-23T12:55:30Z","rating":0,"totalRatings":0,"averageRating":0,"license":{"name":"CC BY-SA","url":"http://creativecommons.org/licenses/by-sa/3.0/ "},"contributors":[{"name":"Thomas LE BOURGEOIS / CIRAD"}],"attributors":[],"annotations":{},"url":"http://portal.wikwio.org/biodiv/img//Celosia trigyna/ceotr_20080609_101206_03.jpg","icon":"http://portal.wikwio.org/biodiv/img//Celosia trigyna/ceotr_20080609_101206_03_th1.jpg"},{"id":934,"description":"Celosia trigyna L.","uploader":{"id":4,"name":"Thomas Le Bourgeois","icon":"http://portal.wikwio.org/biodiv/users//13b7c53d-06c9-4129-9509-346ddce6e458/resources/390_th1.jpg"},"type":"Image","uploadTime":"2015-06-23T12:55:30Z","rating":0,"totalRatings":0,"averageRating":0,"license":{"name":"CC BY-SA","url":"http://creativecommons.org/licenses/by-sa/3.0/ "},"contributors":[{"name":"François KAMGA TCHAYE / CIRAD"}],"attributors":[],"annotations":{},"url":"http://portal.wikwio.org/biodiv/img//Celosia trigyna/ceotr_20020522_144002.jpg","icon":"http://portal.wikwio.org/biodiv/img//Celosia trigyna/ceotr_20020522_144002_th1.jpg"},{"id":935,"description":"Celosia trigyna L.","uploader":{"id":4,"name":"Thomas Le Bourgeois","icon":"http://portal.wikwio.org/biodiv/users//13b7c53d-06c9-4129-9509-346ddce6e458/resources/390_th1.jpg"},"type":"Image","uploadTime":"2015-06-23T12:55:30Z","rating":0,"totalRatings":0,"averageRating":0,"license":{"name":"CC BY-SA","url":"http://creativecommons.org/licenses/by-sa/3.0/ "},"contributors":[{"name":"Michael DEAT / CIRAD"}],"attributors":[],"annotations":{},"url":"http://portal.wikwio.org/biodiv/img//Celosia trigyna/ceotr_20090216_184120.jpg","icon":"http://portal.wikwio.org/biodiv/img//Celosia trigyna/ceotr_20090216_184120_th1.jpg"},{"id":936,"description":"Celosia trigyna L.","uploader":{"id":4,"name":"Thomas Le Bourgeois","icon":"http://portal.wikwio.org/biodiv/users//13b7c53d-06c9-4129-9509-346ddce6e458/resources/390_th1.jpg"},"type":"Image","uploadTime":"2015-06-23T12:55:31Z","rating":0,"totalRatings":0,"averageRating":0,"license":{"name":"CC BY-SA","url":"http://creativecommons.org/licenses/by-sa/3.0/ "},"contributors":[{"name":"Thomas LE BOURGEOIS / CIRAD"}],"attributors":[],"annotations":{},"url":"http://portal.wikwio.org/biodiv/img//Celosia trigyna/ceotr_20080609_101206_02.jpg","icon":"http://portal.wikwio.org/biodiv/img//Celosia trigyna/ceotr_20080609_101206_02_th1.jpg"},{"id":937,"description":"Celosia trigyna L.","uploader":{"id":4,"name":"Thomas Le Bourgeois","icon":"http://portal.wikwio.org/biodiv/users//13b7c53d-06c9-4129-9509-346ddce6e458/resources/390_th1.jpg"},"type":"Image","uploadTime":"2015-06-23T12:55:31Z","rating":0,"totalRatings":0,"averageRating":0,"license":{"name":"CC BY-SA","url":"http://creativecommons.org/licenses/by-sa/3.0/ "},"contributors":[{"name":"Thomas LE BOURGEOIS / CIRAD"}],"attributors":[],"annotations":{},"url":"http://portal.wikwio.org/biodiv/img//Celosia trigyna/ceotr_20090216_190919.jpg","icon":"http://portal.wikwio.org/biodiv/img//Celosia trigyna/ceotr_20090216_190919_th1.jpg"},{"id":939,"description":"Celosia trigyna L.","uploader":{"id":4,"name":"Thomas Le Bourgeois","icon":"http://portal.wikwio.org/biodiv/users//13b7c53d-06c9-4129-9509-346ddce6e458/resources/390_th1.jpg"},"type":"Image","uploadTime":"2015-06-23T12:55:31Z","rating":0,"totalRatings":0,"averageRating":0,"license":{"name":"CC BY-SA","url":"http://creativecommons.org/licenses/by-sa/3.0/ "},"contributors":[{"name":"Michael DEAT / CIRAD"}],"attributors":[],"annotations":{},"url":"http://portal.wikwio.org/biodiv/img//Celosia trigyna/ceotr_20080609_101206_05.jpg","icon":"http://portal.wikwio.org/biodiv/img//Celosia trigyna/ceotr_20080609_101206_05_th1.jpg"},{"id":940,"description":"Celosia trigyna L.","uploader":{"id":4,"name":"Thomas Le Bourgeois","icon":"http://portal.wikwio.org/biodiv/users//13b7c53d-06c9-4129-9509-346ddce6e458/resources/390_th1.jpg"},"type":"Image","uploadTime":"2015-06-23T12:55:30Z","rating":0,"totalRatings":0,"averageRating":0,"license":{"name":"CC BY-SA","url":"http://creativecommons.org/licenses/by-sa/3.0/ "},"contributors":[{"name":"Thomas LE BOURGEOIS / CIRAD"}],"attributors":[],"annotations":{},"url":"http://portal.wikwio.org/biodiv/img//Celosia trigyna/ceotr_20090217_172754.jpg","icon":"http://portal.wikwio.org/biodiv/img//Celosia trigyna/ceotr_20090217_172754_th1.jpg"},{"id":941,"description":"Celosia trigyna L.","uploader":{"id":4,"name":"Thomas Le Bourgeois","icon":"http://portal.wikwio.org/biodiv/users//13b7c53d-06c9-4129-9509-346ddce6e458/resources/390_th1.jpg"},"type":"Image","uploadTime":"2015-06-23T12:55:30Z","rating":0,"totalRatings":0,"averageRating":0,"license":{"name":"CC BY-SA","url":"http://creativecommons.org/licenses/by-sa/3.0/ "},"contributors":[{"name":"Michael DEAT / CIRAD"}],"attributors":[],"annotations":{},"url":"http://portal.wikwio.org/biodiv/img//Celosia trigyna/ceotr_20090217_171749.jpg","icon":"http://portal.wikwio.org/biodiv/img//Celosia trigyna/ceotr_20090217_171749_th1.jpg"},{"id":942,"description":"Celosia trigyna L.","uploader":{"id":4,"name":"Thomas Le Bourgeois","icon":"http://portal.wikwio.org/biodiv/users//13b7c53d-06c9-4129-9509-346ddce6e458/resources/390_th1.jpg"},"type":"Image","uploadTime":"2015-06-23T12:55:30Z","rating":0,"totalRatings":0,"averageRating":0,"license":{"name":"CC BY-SA","url":"http://creativecommons.org/licenses/by-sa/3.0/ "},"contributors":[{"name":"Thomas LE BOURGEOIS / CIRAD"}],"attributors":[],"annotations":{},"url":"http://portal.wikwio.org/biodiv/img//Celosia trigyna/ceotr_20090216_191509.jpg","icon":"http://portal.wikwio.org/biodiv/img//Celosia trigyna/ceotr_20090216_191509_th1.jpg"},{"id":943,"description":"Celosia trigyna L.","uploader":{"id":4,"name":"Thomas Le Bourgeois","icon":"http://portal.wikwio.org/biodiv/users//13b7c53d-06c9-4129-9509-346ddce6e458/resources/390_th1.jpg"},"type":"Image","uploadTime":"2015-06-23T12:55:30Z","rating":0,"totalRatings":0,"averageRating":0,"license":{"name":"CC BY-SA","url":"http://creativecommons.org/licenses/by-sa/3.0/ "},"contributors":[{"name":"Thomas LE BOURGEOIS / CIRAD"}],"attributors":[],"annotations":{},"url":"http://portal.wikwio.org/biodiv/img//Celosia trigyna/ceotr_20090216_184356.jpg","icon":"http://portal.wikwio.org/biodiv/img//Celosia trigyna/ceotr_20090216_184356_th1.jpg"},{"id":20129,"description":"","uploader":{"id":36,"name":"Marnotte Pascal","icon":"http://portal.wikwio.org/biodiv/users//097b0e2c-495a-4219-bf9f-5a2f78a0889c/resources/330_th1.jpg"},"type":"Image","uploadTime":"2016-02-08T09:18:53Z","rating":0,"totalRatings":0,"averageRating":0,"license":{"name":"CC BY","url":"http://creativecommons.org/licenses/by/3.0/"},"contributors":[{"name":"pascal.marnotte"}],"attributors":[],"annotations":{},"url":"http://portal.wikwio.org/biodiv/observations//50aa523c-d0cd-475a-b439-b702c8908760/675.JPG","icon":"http://portal.wikwio.org/biodiv/observations//50aa523c-d0cd-475a-b439-b702c8908760/675_th1.jpg"}],"userGroups":[],"featureCount":0,"featuredNotes":[]}}